Workbook

Sheet fantasycypherrs
A1: Fantasy Name | B1: Nom en Fantasy | C1: Cypher Name | D1: CSR Page | E1: Nom du Cypher | F1: Niveau | G1: Effet
A2: potion of climbing | B2: Potion d’escalade | C2: adhesion | D2: 384 | E2: =VLOOKUP(fantasycypherrs[[#This Row],[Cypher Name]],Sheet1!E:O,11,FALSE()) -> Adhésion | F2: =VLOOKUP(fantasycypherrs[[#This Row],[Cypher Name]],Sheet1!E:O,5,FALSE()) -> 1d6 | G2: =VLOOKUP(fantasycypherrs[[#This Row],[Cypher Name]],Sheet1!E:O,2,FALSE()) -> Permet de grimper automatiquement sur toute les surfaces, màême horizontales. Dure pendant 10 minutes par niveau du cypher.
A3: potion of longevity | B3: Potion de longévité | C3: age taker | D3: 384 | E3: =VLOOKUP(fantasycypherrs[[#This Row],[Cypher Name]],Sheet1!E:O,11,FALSE()) -> Preneur d'à‚ge | F3: =VLOOKUP(fantasycypherrs[[#This Row],[Cypher Name]],Sheet1!E:O,5,FALSE()) -> 1d6 + 4 | G3: =VLOOKUP(fantasycypherrs[[#This Row],[Cypher Name]],Sheet1!E:O,2,FALSE()) -> Commence un processus de rajeunissement qui enlève des années à l'âge physiologique du porteur. Au cours des sept prochains jours, le porteur perd un nombre d'années égal à trois fois le niveau du cypher. Le cypher ne ramène pas l'âge physiologique en dessous de vingt-trois ans.
A4: potion of soothed reflexes | B4: Potion de réflexes | C4: analeptic (level 3–4) | D4: 384 | E4: Analeptique (niveau 3-4) | F4: 1d6 + 2 | G4: Restaure un nombre de points égal au niveau du cypher dans la Réserve de Célérité de l'utilisateur.
A5: potion of greater soothed reflexes | B5: Potion de réflexes améliorée | C5: analeptic (level 5–6) | D5: 384 | E5: Analeptique (niveau 5-6) | F5: 1d6 + 2 | G5: Restaure un nombre de points égal au niveau du cypher dans la Réserve de Célérité de l'utilisateur.
A6: potion of superior soothed reflexes | B6: Potion de réflexes supérieure | C6: analeptic (level 7–8) | D6: 384 | E6: Analeptique (niveau 7-8) | F6: 1d6 + 2 | G6: Restaure un nombre de points égal au niveau du cypher dans la Réserve de Célérité de l'utilisateur.
A7: potion of vitality | B7: Potion de vitalité | C7: antivenom | D7: 384 | E7: =VLOOKUP(fantasycypherrs[[#This Row],[Cypher Name]],Sheet1!E:O,11,FALSE()) -> Antivenin | F7: =VLOOKUP(fantasycypherrs[[#This Row],[Cypher Name]],Sheet1!E:O,5,FALSE()) -> 1d6 + 2 | G7: =VLOOKUP(fantasycypherrs[[#This Row],[Cypher Name]],Sheet1!E:O,2,FALSE()) -> Rend l'utilisateur immunisé contre les poisons d'un niveau inférieur ou égal à celui du cypher pendant une heure par niveau du cypher (et annule tout effet en cours déjà présent dans le système de l'utilisateur).
A8: oil of armor enhancement | B8: Huile d’amélioration d’armure | C8: armor reinforcer | D8: 384 | E8: =VLOOKUP(fantasycypherrs[[#This Row],[Cypher Name]],Sheet1!E:O,11,FALSE()) -> Renforcement d'Armure | F8: =VLOOKUP(fantasycypherrs[[#This Row],[Cypher Name]],Sheet1!E:O,5,FALSE()) -> 1d6 + 1 | G8: =VLOOKUP(fantasycypherrs[[#This Row],[Cypher Name]],Sheet1!E:O,2,FALSE()) -> armure de l'utilisateur bénéficie d'une amélioration pendant vingt-quatre heures. Lancez un d6 pour déterminer le résultat.
A9: scroll of stealing | B9: Parchemin de larcin | C9: attractor | D9: 384 | E9: =VLOOKUP(fantasycypherrs[[#This Row],[Cypher Name]],Sheet1!E:O,11,FALSE()) -> Attracteur | F9: =VLOOKUP(fantasycypherrs[[#This Row],[Cypher Name]],Sheet1!E:O,5,FALSE()) -> 1d6 + 4 | G9: =VLOOKUP(fantasycypherrs[[#This Row],[Cypher Name]],Sheet1!E:O,2,FALSE()) -> Un objet non ancré de la taille de l'utilisateur ou plus petit, situé à longue portée (très longue portée si le niveau du cypher est de 8 ou plus), est immédiatement attiré vers l'utilisateur. Cela prend un tour. L'objet n'a aucun élan lorsqu'il arrive.
A10: oil of aggressive blinking | B10: Huile de clignotement agressif | C10: banishing | D10: 384 | E10: =VLOOKUP(fantasycypherrs[[#This Row],[Cypher Name]],Sheet1!E:O,11,FALSE()) -> Bannissement | F10: =VLOOKUP(fantasycypherrs[[#This Row],[Cypher Name]],Sheet1!E:O,5,FALSE()) -> 1d6 | G10: =VLOOKUP(fantasycypherrs[[#This Row],[Cypher Name]],Sheet1!E:O,2,FALSE()) -> Pendant la journée suivante, chaque fois que l'utilisateur frappe une créature ou un objet solide, cela génère une décharge d'énergie qui téléporte la créature ou l'objet à une distance immédiate dans une direction aléatoire (ni vers le haut ni vers le bas). Les actions de la créature téléportée (y compris la défense) sont entravées à son prochain tour (entravées de deux crans si le niveau du cypher est de 5 ou plus).
A11: carved bone of utility | B11: Os sculpté d’utilité | C11: best tool | D11: 384 | E11: =VLOOKUP(fantasycypherrs[[#This Row],[Cypher Name]],Sheet1!E:O,11,FALSE()) -> Meilleur Outil | F11: =VLOOKUP(fantasycypherrs[[#This Row],[Cypher Name]],Sheet1!E:O,5,FALSE()) -> 1d6 | G11: =VLOOKUP(fantasycypherrs[[#This Row],[Cypher Name]],Sheet1!E:O,2,FALSE()) -> Fournit un atout supplémentaire pour toute tâche utilisant un outil, màême si cela signifie dépasser la limite normale de deux atouts.
A12: scroll of nondetection | B12: Parchemin de non-détection | C12: blackout | D12: 384 | E12: =VLOOKUP(fantasycypherrs[[#This Row],[Cypher Name]],Sheet1!E:O,11,FALSE()) -> Blackout | F12: =VLOOKUP(fantasycypherrs[[#This Row],[Cypher Name]],Sheet1!E:O,5,FALSE()) -> 1d6 + 2 | G12: =VLOOKUP(fantasycypherrs[[#This Row],[Cypher Name]],Sheet1!E:O,2,FALSE()) -> Une zone à portée immédiate de l'utilisateur devient sécurisée contre tout effet extérieur à la zone qui tenterait de voir, d'entendre ou de percevoir ce qui se passe à l'intérieur. Pour les observateurs extérieurs, la zone apparaît comme un "flou" pour tout sens appliqué. Les écoutes, capteurs de divination et autres méthodes de surveillance directe sont également rendus inopérants dans la zone pendant une journée.
A13: oil of defensive blinking | B13: Huile de clignotement défensif | C13: blinking | D13: 385 | E13: =VLOOKUP(fantasycypherrs[[#This Row],[Cypher Name]],Sheet1!E:O,11,FALSE()) -> Clignotement | F13: =VLOOKUP(fantasycypherrs[[#This Row],[Cypher Name]],Sheet1!E:O,5,FALSE()) -> 1d6 | G13: =VLOOKUP(fantasycypherrs[[#This Row],[Cypher Name]],Sheet1!E:O,2,FALSE()) -> Pendant la journée suivante, chaque fois que l'utilisateur est frappé suffisamment fort pour subir des dégâts (mais pas plus d'une fois par tour), il se téléporte à une distance immédiate dans une direction aléatoire (ni vers le haut ni vers le bas). Comme l'utilisateur est préparé à cet effet et que son adversaire ne l'est pas, les défenses de l'utilisateur sont facilitées pendant un tour après la téléportation.
A14: potion of longstrider | B14: Potion de grand-pas | C14: burst of speed | D14: 385 | E14: =VLOOKUP(fantasycypherrs[[#This Row],[Cypher Name]],Sheet1!E:O,11,FALSE()) -> Explosion de Célérité | F14: =VLOOKUP(fantasycypherrs[[#This Row],[Cypher Name]],Sheet1!E:O,5,FALSE()) -> 1d6 | G14: =VLOOKUP(fantasycypherrs[[#This Row],[Cypher Name]],Sheet1!E:O,2,FALSE()) -> Pendant une minute, un utilisateur qui peut normalement se déplacer sur une courte distance en une action peut se déplacer sur une longue distance à la place.
A15: potion of cure disease | B15: Potion de guérison des maladies | C15: catholicon | D15: 385 | E15: =VLOOKUP(fantasycypherrs[[#This Row],[Cypher Name]],Sheet1!E:O,11,FALSE()) -> Catholicon | F15: =VLOOKUP(fantasycypherrs[[#This Row],[Cypher Name]],Sheet1!E:O,5,FALSE()) -> 1d6 + 2 | G15: =VLOOKUP(fantasycypherrs[[#This Row],[Cypher Name]],Sheet1!E:O,2,FALSE()) -> Guérit toute maladie d'un niveau égal ou inférieur à celui du cypher.
A16: potion of magical sorrows | B16: Potion des sanglots magiques | C16: chemical factory | D16: 385 | E16: =VLOOKUP(fantasycypherrs[[#This Row],[Cypher Name]],Sheet1!E:O,11,FALSE()) -> Usine Chimique | F16: =VLOOKUP(fantasycypherrs[[#This Row],[Cypher Name]],Sheet1!E:O,5,FALSE()) -> 1d6 | G16: =VLOOKUP(fantasycypherrs[[#This Row],[Cypher Name]],Sheet1!E:O,2,FALSE()) -> Après une heure, la sueur de l'utilisateur produit 1d6 doses d'un liquide précieux (ces doses ne sont pas considérées comme des cyphers). Elles doivent àêtre utilisées dans la semaine. Lancez un d100 pour déterminer l'effet.
A17: scroll of message | B17: Parchemin de message | C17: Psychic communique | D17: 395 | E17: =VLOOKUP(fantasycypherrs[[#This Row],[Cypher Name]],Sheet1!E:O,11,FALSE()) -> Communication Psychique | F17: =VLOOKUP(fantasycypherrs[[#This Row],[Cypher Name]],Sheet1!E:O,5,FALSE()) -> 1d6 + 2 | G17: =VLOOKUP(fantasycypherrs[[#This Row],[Cypher Name]],Sheet1!E:O,2,FALSE()) -> Permet à l'utilisateur de projeter un message télépathique unique et unidirectionnel de jusqu'à dix mots par niveau de cypher, avec une portée illimitée, à quiconque qu'il connaît.
A18: potion of language comprehension | B18: Potion de compréhension des langues | C18: comprehension | D18: 385 | E18: =VLOOKUP(fantasycypherrs[[#This Row],[Cypher Name]],Sheet1!E:O,11,FALSE()) -> Compréhension | F18: =VLOOKUP(fantasycypherrs[[#This Row],[Cypher Name]],Sheet1!E:O,5,FALSE()) -> 1d6 + 1 | G18: =VLOOKUP(fantasycypherrs[[#This Row],[Cypher Name]],Sheet1!E:O,2,FALSE()) -> En cinq minutes, l'utilisateur peut comprendre les mots d'une langue spécifique liée au cypher (deux langues si le cypher est de niveau 5 ou plus). Cela est vrai màême pour les créatures qui ne possèdent normalement pas de langage. Si l'utilisateur comprenait déjà la langue, le cypher n'a aucun effet. Une fois utilisé, l'effet est permanent et le cypher ne compte plus dans la limite de cyphers qu'un personnage peut porter.
... A21: oil of controlled blinking | B21: Huile de clignotement contrôlé | C21: controlled blinking | D21: 386 | E21: =VLOOKUP(fantasycypherrs[[#This Row],[Cypher Name]],Sheet1!E:O,11,FALSE()) -> Clignotement Contrôlé | F21: =VLOOKUP(fantasycypherrs[[#This Row],[Cypher Name]],Sheet1!E:O,5,FALSE()) -> 1d6 + 2 | G21: =VLOOKUP(fantasycypherrs[[#This Row],[Cypher Name]],Sheet1!E:O,2,FALSE()) -> Pendant la journée suivante, chaque fois que l'utilisateur est frappé suffisamment fort pour subir des dégâts (mais pas plus d'une fois par tour), il se téléporte à un endroit de son choix à portée immédiate. Comme il est préparé à cet effet et que son adversaire ne l'est pas, les défenses de l'utilisateur sont facilitées pendant un tour après la téléportation.
A22: potion of healing | B22: Potion de soin | C22: curative (level 3–4) | D22: 386 | E22: Curatif (niveau 3-4) | F22: 1d6 + 2 | G22: Restaure un nombre de points égal au niveau du cypher dans la Réserve de Puissance de l'utilisateur.
A23: potion of greater healing | B23: Potion de soin améliorée | C23: curative (level 5–6) | D23: 386 | E23: Curatif (niveau 5-6) | F23: 1d6 + 2 | G23: Restaure un nombre de points égal au niveau du cypher dans la Réserve de Puissance de l'utilisateur.
A24: potion of superior healing | B24: Potion de soin supérieure | C24: curative (level 7–8) | D24: 386 | E24: Curatif (niveau 7-8) | F24: 1d6 + 2 | G24: Restaure un nombre de points égal au niveau du cypher dans la Réserve de Puissance de l'utilisateur.
A25: scroll of the unexpected curse | B25: Parchemin de maladie | C25: curse bringer | D25: 386 | E25: =VLOOKUP(fantasycypherrs[[#This Row],[Cypher Name]],Sheet1!E:O,11,FALSE()) -> Porteur de Malédiction | F25: =VLOOKUP(fantasycypherrs[[#This Row],[Cypher Name]],Sheet1!E:O,5,FALSE()) -> 1d6 + 1 | G25: =VLOOKUP(fantasycypherrs[[#This Row],[Cypher Name]],Sheet1!E:O,2,FALSE()) -> Le cypher peut àêtre activé lorsqu'il est donné à une personne qui n'en connaît pas l'importance. La prochaine fois que la victime tente une tâche importante alors qu'elle est en possession du cypher, la tâche est entravée de trois crans.
A26: potion of darksight | B26: Potion de vision nocturne | C26: darksight | D26: 386 | E26: =VLOOKUP(fantasycypherrs[[#This Row],[Cypher Name]],Sheet1!E:O,11,FALSE()) -> Vision Nocturne | F26: =VLOOKUP(fantasycypherrs[[#This Row],[Cypher Name]],Sheet1!E:O,5,FALSE()) -> 1d6 | G26: =VLOOKUP(fantasycypherrs[[#This Row],[Cypher Name]],Sheet1!E:O,2,FALSE()) -> Confère la capacité de voir dans le noir pendant cinq heures par niveau du cypher. (Pour un jeu plus réaliste, ce cypher pourrait plutôt rendre l'utilisateur spécialisé dans la détection en faible luminosité.)
A27: death bringer rune | B27: Rune de mort | C27: death bringer | D27: 386 | E27: =VLOOKUP(fantasycypherrs[[#This Row],[Cypher Name]],Sheet1!E:O,11,FALSE()) -> Porteur de Mort | F27: =VLOOKUP(fantasycypherrs[[#This Row],[Cypher Name]],Sheet1!E:O,5,FALSE()) -> 1d6 | G27: =VLOOKUP(fantasycypherrs[[#This Row],[Cypher Name]],Sheet1!E:O,2,FALSE()) -> Pendant la prochaine minute, lorsque l'utilisateur frappe un PNJ ou une créature d'un niveau égal ou inférieur à celui du cypher, il peut choisir de faire un second jet d'attaque. Si ce second jet d'attaque est une réussite, la cible est tuée. Si la cible est un PJ, le personnage descend d'un cran sur la piste de dégâts.
A28: oil of dense strikes | B28: Huile de frappe forte | C28: density | D28: 386 | E28: =VLOOKUP(fantasycypherrs[[#This Row],[Cypher Name]],Sheet1!E:O,11,FALSE()) -> Densité | F28: =VLOOKUP(fantasycypherrs[[#This Row],[Cypher Name]],Sheet1!E:O,5,FALSE()) -> 1d6 | G28: =VLOOKUP(fantasycypherrs[[#This Row],[Cypher Name]],Sheet1!E:O,2,FALSE()) -> Pendant la journée suivante, chaque fois que l'utilisateur frappe une créature ou un objet solide avec une arme, l'arme voit soudainement son poids augmenter de manière spectaculaire, ce qui inflige 2 points de dégâts supplémentaires.
A29: scroll of fleshbane burst | B29: Parchemin d’explosion nécrotique | C29: detonation (cell-disrupting) | D29: 386 | E29: Détonation (nécrose des chairs) | F29: 1d6 + 2 | G29: Projette un petit explosif physique jusqu'à longue distance qui explose dans un rayon immédiat, infligeant des dégâts égaux au niveau du cypher.
A30: scroll of frost burst | B30: Parchemin d’explosion de froid | C30: detonation (cold) | D30: 386 | E30: Détonation (froid) | F30: 1d6 + 2 | G30: Projette un petit explosif physique jusqu'à longue distance qui explose dans un rayon immédiat, infligeant des dégâts égaux au niveau du cypher.
A31: scroll of acid burst | B31: Parchemin d’explosion d’acide | C31: detonation (corrosive) | D31: 386 | E31: Détonation (Corrosif) | F31: 1d6 + 2 | G31: Projette un petit explosif physique jusqu'à longue distance qui explose dans un rayon immédiat, infligeant des dégâts égaux au niveau du cypher.
A32: gem of monster summoning | B32: Gemme d’invocation de monstre | C32: detonation (creature) | D32: 386 | E32: =VLOOKUP(fantasycypherrs[[#This Row],[Cypher Name]],Sheet1!E:O,11,FALSE()) -> Détonation (Créature) | F32: =VLOOKUP(fantasycypherrs[[#This Row],[Cypher Name]],Sheet1!E:O,5,FALSE()) -> 1d6 + 1 | G32: =VLOOKUP(fantasycypherrs[[#This Row],[Cypher Name]],Sheet1!E:O,2,FALSE()) -> Projette un petit explosif physique jusqu'à longue distance qui explose et crée un portail de téléportation temporaire. Une créature aléatoire dont le niveau est inférieur ou égal à celui du cypher apparaît à travers le portail et attaque la cible la plus proche. Au bout d'environ une minute, la créature disparaît.
A33: scroll of withering burst | B33: Parchemin d’explosion desséchante | C33: detonation (desiccating) | D33: 386 | E33: =VLOOKUP(fantasycypherrs[[#This Row],[Cypher Name]],Sheet1!E:O,11,FALSE()) -> Détonation (Desséchant) | F33: =VLOOKUP(fantasycypherrs[[#This Row],[Cypher Name]],Sheet1!E:O,5,FALSE()) -> 1d6 + 2 | G33: =VLOOKUP(fantasycypherrs[[#This Row],[Cypher Name]],Sheet1!E:O,2,FALSE()) -> Projette un petit explosif physique jusqu'à longue distance qui éclate dans un rayon immédiat, drainant l'humidité de tout ce qui s'y trouve. Les créatures vivantes subissent des dégâts égaux au niveau du cypher. L'eau présente dans la zone est vaporisée.
A34: scroll of lightning burst | B34: Parchemin d’explosion électrique | C34: detonation (electrical discharge) | D34: 386 | E34: Détonation (électrique) | F34: 1d6 + 2 | G34: Projette un petit explosif physique jusqu'à longue distance qui explose dans un rayon immédiat, infligeant des dégâts égaux au niveau du cypher.
A35: scroll of flame burst | B35: Parchemin d’explosion de feu | C35: detonation (fire) | D35: 386 | E35: Détonation (feu) | F35: 1d6 + 2 | G35: Projette un petit explosif physique jusqu'à longue distance qui explose dans un rayon immédiat, infligeant des dégâts de feu égaux au niveau du cypher.
A36: scroll of blindness | B36: Parchemin de cécité | C36: detonation (flash) | D36: 386 | E36: =VLOOKUP(fantasycypherrs[[#This Row],[Cypher Name]],Sheet1!E:O,11,FALSE()) -> Détonation (Flash) | F36: =VLOOKUP(fantasycypherrs[[#This Row],[Cypher Name]],Sheet1!E:O,5,FALSE()) -> 1d6 + 2 | G36: =VLOOKUP(fantasycypherrs[[#This Row],[Cypher Name]],Sheet1!E:O,2,FALSE()) -> Projette un petit explosif physique jusqu'à longue distance qui éclate dans un rayon immédiat, aveuglant tous ceux qui s'y trouvent pendant une minute (dix minutes si le cypher est de niveau 4 ou plus).
A37: scroll of reverse gravity | B37: Parchemin d’inversion de la gravité | C37: detonation (gravity inversion) | D37: 387 | E37: =VLOOKUP(fantasycypherrs[[#This Row],[Cypher Name]],Sheet1!E:O,11,FALSE()) -> Détonation (Inversion Gravitationnelle) | F37: =VLOOKUP(fantasycypherrs[[#This Row],[Cypher Name]],Sheet1!E:O,5,FALSE()) -> 1d6 + 1 | G37: =VLOOKUP(fantasycypherrs[[#This Row],[Cypher Name]],Sheet1!E:O,2,FALSE()) -> Projette un petit explosif physique jusqu'à longue distance qui explose, et pendant une heure, la gravité est inversée dans un rayon long autour de l'explosion.
A38: scroll of invisible weights | B38: Parchemin des poids invisibles | C38: detonation (gravity) | D38: 387 | E38: =VLOOKUP(fantasycypherrs[[#This Row],[Cypher Name]],Sheet1!E:O,11,FALSE()) -> Détonation (Gravité) | F38: =VLOOKUP(fantasycypherrs[[#This Row],[Cypher Name]],Sheet1!E:O,5,FALSE()) -> 1d6 + 2 | G38: =VLOOKUP(fantasycypherrs[[#This Row],[Cypher Name]],Sheet1!E:O,2,FALSE()) -> ProjetteDetonation (Gravity) un petit explosif physique jusqu'à longue distance qui éclate dans un rayon immédiat, infligeant des dégâts égaux au niveau du cypher en augmentant fortement la gravité pendant une seconde. Toutes les créatures dans la zone sont écrasées au sol pendant un tour et ne peuvent pas effectuer d'actions physiques.
A39: scroll of enlarged fleshbane burst | B39: Parchemin d’explosion nécrotique étendue | C39: detonation (massive,cell-disrupting) | D39: 387 | E39: Détonation (Massive, nécrose des chairs) | F39: 1d6 + 2 | G39: Projette un petit explosif physique jusqu'à longue distance qui explose dans un rayon de courte portée, infligeant des dégâts de nécrose des chairs égaux au niveau du cypher.
A40: scroll of enlarged frost burst | B40: Parchemin d’explosion de froid étendue | C40: detonation (massive,cold) | D40: 387 | E40: Détonation (Massive, froid) | F40: 1d6 + 2 | G40: Projette un petit explosif physique jusqu'à longue distance qui explose dans un rayon de courte portée, infligeant des dégâts de froid égaux au niveau du cypher.
A41: scroll of enlarged acid burst | B41: Parchemin d’explosion d’acide étendue | C41: detonation (massive,corrosive) | D41: 387 | E41: Détonation (Massive, corrosif) | F41: 1d6 + 2 | G41: Projette un petit explosif physique jusqu'à longue distance qui explose dans un rayon immédiat, infligeant des dégâts corrosifs égaux au niveau du cypher.
A42: scroll of enlarged lightning burst | B42: Parchemin d’explosion électrique étendue | C42: detonation (massive,electrical discharge) | D42: 387 | E42: Détonation (Massive, électrique) | F42: 1d6 + 2 | G42: Projette un petit explosif physique jusqu'à longue distance qui explose dans un rayon de courte portée, infligeant des dégâts électriques égaux au niveau du cypher.
A43: scroll of enlarged flame burst | B43: Parchemin d’explosion de feu étendue | C43: detonation (massive,fire) | D43: 387 | E43: Détonation (Massive, feu) | F43: 1d6 + 2 | G43: Projette un petit explosif physique jusqu'à longue distance qui explose dans un rayon de courte portée, infligeant des dégâts de feu égaux au niveau du cypher.
A44: scroll of enlarged dagger burst | B44: Parchemin d’explosion de dagues étendue | C44: detonation (massive,shrapnel) | D44: 387 | E44: Détonation (Massive, éclats) | F44: 1d6 + 2 | G44: Projette un petit explosif physique jusqu'à longue distance qui explose dans un rayon de courte portée, infligeant des dégâts coupants égaux au niveau du cypher.
A45: scroll of chaos burst | B45: Parchemin d’explosion de chaos | C45: detonation (matter disruption) | D45: 387 | E45: =VLOOKUP(fantasycypherrs[[#This Row],[Cypher Name]],Sheet1!E:O,11,FALSE()) -> Détonation (Perturbation de la Matière) | F45: 1d6 + 2 | G45: =VLOOKUP(fantasycypherrs[[#This Row],[Cypher Name]],Sheet1!E:O,2,FALSE()) -> Projette un petit explosif physique jusqu'à longue distance qui explose dans un rayon immédiat, libérant des nanites qui réarrangent la matière de manière aléatoire. Inflige des dégâts égaux au niveau du cypher.
A46: scroll of hammer burst | B46: Parchemin d’explosion de marteaux | C46: detonation (pressure) | D46: 387 | E46: =VLOOKUP(fantasycypherrs[[#This Row],[Cypher Name]],Sheet1!E:O,11,FALSE()) -> Détonation (Pression) | F46: =VLOOKUP(fantasycypherrs[[#This Row],[Cypher Name]],Sheet1!E:O,5,FALSE()) -> 1d6 + 2 | G46: =VLOOKUP(fantasycypherrs[[#This Row],[Cypher Name]],Sheet1!E:O,2,FALSE()) -> Projette un petit explosif physique jusqu'à longue distance qui explose dans un rayon immédiat, infligeant des dégâts d'impact égaux au niveau du cypher. Déplace également les objets non surveillés hors de la zone s'ils pèsent moins de 20 livres (9 kg) par niveau du cypher.
A47: scroll of dagger burst | B47: Parchemin d’explosion de dagues étendue | C47: detonation (shrapnel) | D47: 386 | E47: Détonation (éclats) | F47: 1d6 + 2 | G47: Projette un petit explosif physique jusqu'à longue distance qui explose dans un rayon immédiat, infligeant des dégâts égaux au niveau du cypher.
A48: scroll of annihilation | C48: detonation (singularity) | D48: 387 | E48: =VLOOKUP(fantasycypherrs[[#This Row],[Cypher Name]],Sheet1!E:O,11,FALSE()) -> Détonation (Singularité) | F48: =VLOOKUP(fantasycypherrs[[#This Row],[Cypher Name]],Sheet1!E:O,5,FALSE()) -> 10 | G48: =VLOOKUP(fantasycypherrs[[#This Row],[Cypher Name]],Sheet1!E:O,2,FALSE()) -> Projette un petit explosif physique jusqu'à longue distance qui explose et crée une singularité momentanée qui déchire le tissu de l'univers. Inflige 20 points de dégâts à tous ceux dans un rayon court, les attirant (ou leurs restes) vers un rayon immédiat (si possible). Les personnages joueurs dans le rayon qui échouent à un jet de défense en Puissance descendent d'un cran sur la piste de dégâts.
A49: scroll of deafness | C49: detonation (sonic) | D49: 387 | E49: =VLOOKUP(fantasycypherrs[[#This Row],[Cypher Name]],Sheet1!E:O,11,FALSE()) -> Détonation (Sonique) | F49: =VLOOKUP(fantasycypherrs[[#This Row],[Cypher Name]],Sheet1!E:O,5,FALSE()) -> 1d6 + 2 | G49: =VLOOKUP(fantasycypherrs[[#This Row],[Cypher Name]],Sheet1!E:O,2,FALSE()) -> Projette un petit explosif physique jusqu'à longue distance qui explose avec un bruit terrifiant, rendant sourds tous ceux dans un rayon immédiat pendant dix minutes par niveau du cypher.
A50: scroll of chain fleshbane burst | B50: Parchemin d’explosions en chaîne nécrotique | C50: detonation (spawn,cell-disrupting) | D50: 387 | E50: Détonation (Prolifération, nécrose des chairs) | F50: 1d6 + 2 | G50: Projette un petit explosif physique jusqu'à longue distance qui éclate dans un rayon immédiat, aveuglant tous ceux qui s'y trouvent pendant une minute et infligeant des dégâts de nécrose des chairs égaux au niveau du cypher. L'explosion génère 1d6 détonations supplémentaires ; au tour suivant, chaque nouvelle détonation se dirige vers un endroit aléatoire dans un rayon court et explose dans un rayon immédiat. Lancez un d100 pour déterminer le type de dégâts infligés par toutes les détonations :
A51: scroll of chain frost burst | B51: Parchemin d’explosions en chaîne de froid | C51: detonation (spawn,cold) | D51: 387 | E51: Détonation (Prolifération, froid) | F51: 1d6 + 2 | G51: Projette un petit explosif physique jusqu'à longue distance qui éclate dans un rayon immédiat, aveuglant tous ceux qui s'y trouvent pendant une minute et infligeant des dégâts de froid égaux au niveau du cypher. L'explosion génère 1d6 détonations supplémentaires ; au tour suivant, chaque nouvelle détonation se dirige vers un endroit aléatoire dans un rayon court et explose dans un rayon immédiat. Lancez un d100 pour déterminer le type de dégâts infligés par toutes les détonations :
A52: scroll of chain acid burst | B52: Parchemin d’explosions en chaîne d’acide | C52: detonation (spawn,corrosive) | D52: 387 | E52: Détonation (Prolifération, Corrosif) | F52: 1d6 + 2 | G52: Projette un petit explosif physique jusqu'à longue distance qui éclate dans un rayon immédiat, aveuglant tous ceux qui s'y trouvent pendant une minute et infligeant des dégâts corrosifs égaux au niveau du cypher. L'explosion génère 1d6 détonations supplémentaires ; au tour suivant, chaque nouvelle détonation se dirige vers un endroit aléatoire dans un rayon court et explose dans un rayon immédiat. Lancez un d100 pour déterminer le type de dégâts infligés par toutes les détonations :
A53: scroll of chain lightning burst | B53: Parchemin d’explosions en chaîne électrique | C53: detonation (spawn,electrical discharge) | D53: 387 | E53: Détonation (Prolifération, électrique) | F53: 1d6 + 2 | G53: Projette un petit explosif physique jusqu'à longue distance qui éclate dans un rayon immédiat, aveuglant tous ceux qui s'y trouvent pendant une minute et infligeant des dégâts électriques égaux au niveau du cypher. L'explosion génère 1d6 détonations supplémentaires ; au tour suivant, chaque nouvelle détonation se dirige vers un endroit aléatoire dans un rayon court et explose dans un rayon immédiat. Lancez un d100 pour déterminer le type de dégâts infligés par toutes les détonations :
A54: scroll of chain flame burst | B54: Parchemin d’explosions en chaîne de feu | C54: detonation (spawn,fire) | D54: 387 | E54: Détonation (Prolifération, feu) | F54: 1d6 + 2 | G54: Projette un petit explosif physique jusqu'à longue distance qui éclate dans un rayon immédiat, aveuglant tous ceux qui s'y trouvent pendant une minute et infligeant des dégâts de feu égaux au niveau du cypher. L'explosion génère 1d6 détonations supplémentaires ; au tour suivant, chaque nouvelle détonation se dirige vers un endroit aléatoire dans un rayon court et explose dans un rayon immédiat. Lancez un d100 pour déterminer le type de dégâts infligés par toutes les détonations :
A55: scroll of chain dagger burst | B55: Parchemin d’explosions en chaîne de dagues | C55: detonation (spawn,shrapnel) | D55: 387 | E55: Détonation (Prolifération, éclats) | F55: 1d6 + 2 | G55: Projette un petit explosif physique jusqu'à longue distance qui éclate dans un rayon immédiat, aveuglant tous ceux qui s'y trouvent pendant une minute et infligeant des dégâts coupants égaux au niveau du cypher. L'explosion génère 1d6 détonations supplémentaires ; au tour suivant, chaque nouvelle détonation se dirige vers un endroit aléatoire dans un rayon court et explose dans un rayon immédiat. Lancez un d100 pour déterminer le type de dégâts infligés par toutes les détonations :
A56: scroll of web | B56: Parchemin de toile d’araignée | C56: detonation (web) | D56: 387 | E56: =VLOOKUP(fantasycypherrs[[#This Row],[Cypher Name]],Sheet1!E:O,11,FALSE()) -> Détonation (Toile) | F56: =VLOOKUP(fantasycypherrs[[#This Row],[Cypher Name]],Sheet1!E:O,5,FALSE()) -> 1d6 + 2 | G56: =VLOOKUP(fantasycypherrs[[#This Row],[Cypher Name]],Sheet1!E:O,2,FALSE()) -> Projette un petit explosif physique jusqu'à longue distance qui explose dans un rayon immédiat et crée des filaments collants. Les PJ pris dans la zone doivent réussir une action basée sur la Puissance pour s'en sortir, avec une difficulté déterminée par le niveau du cypher. Les PNJ se libèrent si leur niveau est supérieur à celui du cypher.
A57: rune of disarming | C57: disarm | D57: 387 | E57: =VLOOKUP(fantasycypherrs[[#This Row],[Cypher Name]],Sheet1!E:O,11,FALSE()) -> Désarmement | F57: =VLOOKUP(fantasycypherrs[[#This Row],[Cypher Name]],Sheet1!E:O,5,FALSE()) -> 1d6 + 1 | G57: =VLOOKUP(fantasycypherrs[[#This Row],[Cypher Name]],Sheet1!E:O,2,FALSE()) -> Un PNJ dans un rayon immédiat dont le niveau est inférieur à celui du cypher laisse tomber ce qu'il tient.
A58: potion of disguise | C58: disguise module | D58: 388 | E58: =VLOOKUP(fantasycypherrs[[#This Row],[Cypher Name]],Sheet1!E:O,11,FALSE()) -> Module de Déguisement | F58: =VLOOKUP(fantasycypherrs[[#This Row],[Cypher Name]],Sheet1!E:O,5,FALSE()) -> 1d6 + 2 | G58: =VLOOKUP(fantasycypherrs[[#This Row],[Cypher Name]],Sheet1!E:O,2,FALSE()) -> Pendant les dix minutes suivantes par niveau du cypher, les traits de l'utilisateur deviennent presque identiques à ceux d'une personne désignée avec laquelle il a déjà interagi, facilitant de deux crans les tentatives de se faire passer pour cette personne. Une fois désignée, l'utilisateur ne peut plus modifier l'effet pour ressembler à une autre personne, bien qu'il puisse retirer le module pour retrouver son apparence avant la fin de la durée.
A59: oil of fleshbane | C59: disrupting | D59: 388 | E59: =VLOOKUP(fantasycypherrs[[#This Row],[Cypher Name]],Sheet1!E:O,11,FALSE()) -> Perturbation | F59: =VLOOKUP(fantasycypherrs[[#This Row],[Cypher Name]],Sheet1!E:O,5,FALSE()) -> 1d6 | G59: =VLOOKUP(fantasycypherrs[[#This Row],[Cypher Name]],Sheet1!E:O,2,FALSE()) -> Pour la prochaine journée, chaque fois que l'utilisateur frappe une créature solide ou un objet, l'attaque génère une explosion de nanites qui attaquent directement ses cellules organiques. La cible subit 1 point de dégât supplémentaire. Si le niveau de la cible est inférieur à celui du cypher, elle perd sa prochaine action ; sinon, sa prochaine action est entravée.
A60: potion of eagle eye | C60: eagleseye | D60: 388 | E60: =VLOOKUP(fantasycypherrs[[#This Row],[Cypher Name]],Sheet1!E:O,11,FALSE()) -> Oeil d'Aigle | F60: =VLOOKUP(fantasycypherrs[[#This Row],[Cypher Name]],Sheet1!E:O,5,FALSE()) -> 1d6 | G60: =VLOOKUP(fantasycypherrs[[#This Row],[Cypher Name]],Sheet1!E:O,2,FALSE()) -> Donne la capacité de voir dix fois plus loin que la normale pendant une heure par niveau du cypher. (Pour un jeu plus réaliste, le cypher Å“il d'aigle pourrait à la place accorder deux atouts pour les tâches impliquant la vision à longue distance.)
A61: potion of energy resistance | C61: effect resistance | D61: 388 | E61: =VLOOKUP(fantasycypherrs[[#This Row],[Cypher Name]],Sheet1!E:O,11,FALSE()) -> Résistance aux Effets | F61: =VLOOKUP(fantasycypherrs[[#This Row],[Cypher Name]],Sheet1!E:O,5,FALSE()) -> 1d6 + 1 | G61: =VLOOKUP(fantasycypherrs[[#This Row],[Cypher Name]],Sheet1!E:O,2,FALSE()) -> Fournit une chance de résistance supplémentaire aux effets directement dommageables de toutes sortes, tels que le feu, la foudre, etc., pendant une journée. (Cela ne fournit pas de résistance contre les attaques contondantes, tranchantes ou perforantes.) Si le niveau de l'effet est inférieur ou égal à celui du cypher, l'utilisateur obtient un jet de défense supplémentaire pour l'éviter. En cas de réussite, l'attaque est traitée comme si l'utilisateur avait réussi son jet de défense habituel. (Si l'utilisateur est un PNJ, un PJ qui l'attaque avec ce genre d'effet doit réussir deux jets d'attaque pour lui infliger des dégâts.)
A62: potion of enhancement | C62: effort enhancer (combat) | D62: 388 | E62: =VLOOKUP(fantasycypherrs[[#This Row],[Cypher Name]],Sheet1!E:O,11,FALSE()) -> Amplificateur d'Effort (Combat) | F62: =VLOOKUP(fantasycypherrs[[#This Row],[Cypher Name]],Sheet1!E:O,5,FALSE()) -> 1d6 + 1 | G62: =VLOOKUP(fantasycypherrs[[#This Row],[Cypher Name]],Sheet1!E:O,2,FALSE()) -> Pour l'heure suivante, l'utilisateur peut appliquer un niveau gratuit d'Effort à n'importe quelle tâche (y compris une tâche de combat) sans dépenser de points de Réserve. Le niveau gratuit d'Effort fourni par ce cypher ne compte pas dans le maximum d'Effort qu'un personnage peut normalement appliquer à une tâche. Une fois ce niveau gratuit d'Effort utilisé, l'effet du cypher prend fin.
A63: potion of peaceful enhancement | C63: effort enhancer (noncombat) | D63: 388 | E63: =VLOOKUP(fantasycypherrs[[#This Row],[Cypher Name]],Sheet1!E:O,11,FALSE()) -> Amplificateur d'Effort (Non-combat) | F63: =VLOOKUP(fantasycypherrs[[#This Row],[Cypher Name]],Sheet1!E:O,5,FALSE()) -> 1d6 | G63: =VLOOKUP(fantasycypherrs[[#This Row],[Cypher Name]],Sheet1!E:O,2,FALSE()) -> Pour l'heure suivante, l'utilisateur peut appliquer un niveau gratuit d'Effort à une tâche non-combat sans dépenser de points de Réserve. Le niveau d'Effort fourni par ce cypher ne compte pas dans le maximum d'Effort qu'un personnage peut normalement appliquer à une tâche. Une fois ce niveau gratuit d'Effort utilisé, l'effet du cypher prend fin.
A64: potion of shield | C64: enduring shield | D64: 388 | E64: =VLOOKUP(fantasycypherrs[[#This Row],[Cypher Name]],Sheet1!E:O,11,FALSE()) -> Bouclier Durable | F64: =VLOOKUP(fantasycypherrs[[#This Row],[Cypher Name]],Sheet1!E:O,5,FALSE()) -> 1d6 + 4 | G64: =VLOOKUP(fantasycypherrs[[#This Row],[Cypher Name]],Sheet1!E:O,2,FALSE()) -> Pour la prochaine journée, l'utilisateur bénéficie d'un atout pour les jets de défense en Célérité.
A65: marvelous painting kit | C65: equipment cache | D65: 388 | E65: =VLOOKUP(fantasycypherrs[[#This Row],[Cypher Name]],Sheet1!E:O,11,FALSE()) -> Cache d'Equipement | F65: =VLOOKUP(fantasycypherrs[[#This Row],[Cypher Name]],Sheet1!E:O,5,FALSE()) -> 1d6 + 1 | G65: =VLOOKUP(fantasycypherrs[[#This Row],[Cypher Name]],Sheet1!E:O,2,FALSE()) -> L'utilisateur peut fouiller dans le cypher et produire un équipement désiré (pas un artefact) dont le niveau ne dépasse pas celui du cypher. L'équipement persiste jusqu'à une journée, sauf si sa nature fondamentale permet un usage unique (comme une grenade).
A66: scroll of scrying | C66: farsight | D66: 388 | E66: =VLOOKUP(fantasycypherrs[[#This Row],[Cypher Name]],Sheet1!E:O,11,FALSE()) -> Vision à Distance | F66: =VLOOKUP(fantasycypherrs[[#This Row],[Cypher Name]],Sheet1!E:O,5,FALSE()) -> 1d6 + 1 | G66: =VLOOKUP(fantasycypherrs[[#This Row],[Cypher Name]],Sheet1!E:O,2,FALSE()) -> L'utilisateur peut observer un endroit qu'il a déjà visité, peu importe la distance (màême à travers des galaxies). Cette vision persiste pendant dix minutes par niveau du cypher. Le personnage peut alterner entre la vision de cet endroit et celle de son emplacement actuel une fois par round.
A67: oil of fireproofing | C67: fireproofing | D67: 388 | E67: =VLOOKUP(fantasycypherrs[[#This Row],[Cypher Name]],Sheet1!E:O,11,FALSE()) -> Résistance au Feu | F67: =VLOOKUP(fantasycypherrs[[#This Row],[Cypher Name]],Sheet1!E:O,5,FALSE()) -> 1d6 + 4 | G67: =VLOOKUP(fantasycypherrs[[#This Row],[Cypher Name]],Sheet1!E:O,2,FALSE()) -> Un objet inanimé traité par ce cypher bénéficie d'une Armure contre les dégâts de feu égale au niveau du cypher pendant une journée.
A68: scroll of flame extinguishing | C68: flame-retardant wall | D68: 388 | E68: =VLOOKUP(fantasycypherrs[[#This Row],[Cypher Name]],Sheet1!E:O,11,FALSE()) -> Mur Ignifuge | F68: =VLOOKUP(fantasycypherrs[[#This Row],[Cypher Name]],Sheet1!E:O,5,FALSE()) -> 1d6 | G68: =VLOOKUP(fantasycypherrs[[#This Row],[Cypher Name]],Sheet1!E:O,2,FALSE()) -> Crée un plan immobile d'énergie perméable mesurant jusqu'à 6 m par 6 m (20 pieds par 20 pieds) pendant une heure par niveau du cypher. Le plan se conforme à l'espace disponible. Les flammes passant à travers le plan sont éteintes.
... A74: scroll of winter wall | C74: frigid wall | D74: 389 | E74: =VLOOKUP(fantasycypherrs[[#This Row],[Cypher Name]],Sheet1!E:O,11,FALSE()) -> Mur Frigorifique | F74: =VLOOKUP(fantasycypherrs[[#This Row],[Cypher Name]],Sheet1!E:O,5,FALSE()) -> 1d6 + 2 | G74: =VLOOKUP(fantasycypherrs[[#This Row],[Cypher Name]],Sheet1!E:O,2,FALSE()) -> Crée un mur d'air super-refroidi mesurant jusqu'à 9 m par 9 m par 30 cm (30 pieds par 30 pieds par 1 pied) qui inflige des dégâts égaux au niveau du cypher à tout ce qui le traverse. Le mur se conforme à l'espace disponible et dure dix minutes.
A75: scroll of the amnesiac cloud | C75: gas bomb (amnesia gas) | D75: 389 | E75: Bombe à Gaz (Gaz d'amnésie) | F75: 1d6 + 2 | G75: Lancée à courte distance, elle explose en un nuage empoisonné couvrant une zone immédiate. Le nuage persiste pendant 1d6 rounds, sauf si les conditions l'indiquent autrement. Gaz d'amnésie : les créatures vivantes qui respirent et pensent perdent définitivement toute mémoire de la dernière minute.
A76: dust of choking | C76: gas bomb (choking gas) | D76: 389 | E76: Bombe à Gaz (Gaz d'étouffement) | F76: 1d6 + 2 | G76: Lancée à courte distance, elle explose en un nuage empoisonné couvrant une zone immédiate. Le nuage persiste pendant 1d6 rounds, sauf si les conditions l'indiquent autrement. Gaz d'étouffement : les créatures vivantes qui respirent perdent leurs actions à cause de l'étouffement et de la toux pendant un nombre de rounds égal au niveau du cypher.
A77: scroll of acid cloud | C77: gas bomb (corrosive gas) | D77: 389 | E77: Bombe à Gaz (Gaz corrosif) | F77: 1d6 + 2 | G77: Lancée à courte distance, elle explose en un nuage empoisonné couvrant une zone immédiate. Le nuage persiste pendant 1d6 rounds, sauf si les conditions l'indiquent autrement. Gaz corrosif : tout subit des dégâts égaux au niveau du cypher.
A78: scroll of fear gas | C78: gas bomb (fear gas) | D78: 389 | E78: Bombe à Gaz (Gaz de peur) | F78: 1d6 + 2 | G78: Lancée à courte distance, elle explose en un nuage empoisonné couvrant une zone immédiate. Le nuage persiste pendant 1d6 rounds, sauf si les conditions l'indiquent autrement. Gaz de peur : les créatures vivantes qui respirent et pensent fuient dans une direction aléatoire de peur (ou sont paralysées par la peur) pendant un nombre de rounds égal au niveau du cypher.
A79: scroll of dream vapors | C79: gas bomb (hallucinogenic gas) | D79: 389 | E79: Bombe à Gaz (Gaz hallucinogène) | F79: 1d6 + 2 | G79: Lancée à courte distance, elle explose en un nuage empoisonné couvrant une zone immédiate. Le nuage persiste pendant 1d6 rounds, sauf si les conditions l'indiquent autrement. Gaz hallucinogène : les créatures vivantes qui respirent perdent leurs actions à cause des hallucinations et visions pendant un nombre de rounds égal au niveau du cypher.
A80: scroll of mindbane vapors | C80: gas bomb (mind-numbing gas) | D80: 389 | E80: Bombe à Gaz ( Gaz débilitant) | F80: 1d6 + 2 | G80: Lancée à courte distance, elle explose en un nuage empoisonné couvrant une zone immédiate. Le nuage persiste pendant 1d6 rounds, sauf si les conditions l'indiquent autrement. Gaz débilitant : les créatures vivantes qui respirent subissent des dégâts en Intellect égaux au niveau du cypher.
A81: scroll of numbing vapors | C81: gas bomb (nerve gas) | D81: 389 | E81: Bombe à Gaz ( Gaz neurotoxique) | F81: 1d6 + 2 | G81: Lancée à courte distance, elle explose en un nuage empoisonné couvrant une zone immédiate. Le nuage persiste pendant 1d6 rounds, sauf si les conditions l'indiquent autrement. Gaz neurotoxique : les créatures vivantes qui respirent subissent des dégâts en Célérité égaux au niveau du cypher.
A82: scroll of poisonous cloud | C82: gas bomb (poison gas) | D82: 389 | E82: Bombe à Gaz (Gaz empoisonné) | F82: 1d6 + 2 | G82: Lancée à courte distance, elle explose en un nuage empoisonné couvrant une zone immédiate. Le nuage persiste pendant 1d6 rounds, sauf si les conditions l'indiquent autrement. Gaz empoisonné : les créatures vivantes qui respirent subissent des dégâts égaux au niveau du cypher.
A83: scroll of berserk vapors | C83: gas bomb (rage gas) | D83: 389 | E83: Bombe à Gaz (Gaz de rage) | F83: 1d6 + 2 | G83: Lancée à courte distance, elle explose en un nuage empoisonné couvrant une zone immédiate. Le nuage persiste pendant 1d6 rounds, sauf si les conditions l'indiquent autrement. Gaz de rage : les créatures vivantes qui respirent et pensent attaquent au corps à corps la créature la plus proche et continuent à le faire pendant un nombre de rounds égal au niveau du cypher.
A84: scroll of sleep gas | C84: gas bomb (sleep gas) | D84: 389 | E84: Bombe à Gaz (Gaz soporifique) | F84: 1d6 + 2 | G84: Lancée à courte distance, elle explose en un nuage empoisonné couvrant une zone immédiate. Le nuage persiste pendant 1d6 rounds, sauf si les conditions l'indiquent autrement. Gaz soporifique : les créatures vivantes qui respirent s'endorment pendant un nombre de rounds égal au niveau du cypher ou jusqu'à ce qu'elles soient réveillées par une action violente ou un bruit extrêmement fort.
A85: scroll of smoke burst | C85: gas bomb (thick smoke) | D85: 389 | E85: Bombe à Gaz (Fumée épaisse) | F85: 1d6 + 2 | G85: Lancée à courte distance, elle explose en un nuage empoisonné couvrant une zone immédiate. Le nuage persiste pendant 1d6 rounds, sauf si les conditions l'indiquent autrement. Fumée épaisse : occulte la vue tant que le nuage persiste
A86: potion of levitation | C86: gravity nullifier | D86: 390 | E86: =VLOOKUP(fantasycypherrs[[#This Row],[Cypher Name]],Sheet1!E:O,11,FALSE()) -> Nullificateur de Gravité | F86: =VLOOKUP(fantasycypherrs[[#This Row],[Cypher Name]],Sheet1!E:O,5,FALSE()) -> 1d6 + 3 | G86: =VLOOKUP(fantasycypherrs[[#This Row],[Cypher Name]],Sheet1!E:O,2,FALSE()) -> Pendant une heure, l'utilisateur peut flotter dans les airs, se déplaà§ant verticalement d'une courte distance par round (mais pas horizontalement sans une autre action, comme se pousser contre un plafond). L'utilisateur doit peser moins de 23 kg (50 livres) par niveau du cypher.
A87: oil of hovering | C87: gravity-nullifying application | D87: 390 | E87: =VLOOKUP(fantasycypherrs[[#This Row],[Cypher Name]],Sheet1!E:O,11,FALSE()) -> Application Nullifiant la Gravité | F87: =VLOOKUP(fantasycypherrs[[#This Row],[Cypher Name]],Sheet1!E:O,5,FALSE()) -> 1d6 + 2 | G87: =VLOOKUP(fantasycypherrs[[#This Row],[Cypher Name]],Sheet1!E:O,2,FALSE()) -> Si un objet non vivant ne dépassant pas la taille d'un humain (deux humains si le niveau du cypher est 6 ou plus) est recouvert par ce cypher, il flotte à une hauteur de 1d20 pieds dans les airs de manière permanente et n'a plus de poids s'il est porté (bien qu'il doive àêtre solidement attaché).
A88: oil of flame burst | C88: heat attack | D88: 390 | E88: =VLOOKUP(fantasycypherrs[[#This Row],[Cypher Name]],Sheet1!E:O,11,FALSE()) -> Attaque de Chaleur | F88: =VLOOKUP(fantasycypherrs[[#This Row],[Cypher Name]],Sheet1!E:O,5,FALSE()) -> 1d6 | G88: =VLOOKUP(fantasycypherrs[[#This Row],[Cypher Name]],Sheet1!E:O,2,FALSE()) -> Pendant la journée suivante, chaque fois que l'utilisateur frappe une créature ou un objet solide, l'attaque génère une explosion de chaleur qui inflige 2 points de dégâts supplémentaires.
A89: tenacious dart | C89: hunter/seeker | D89: 390 | E89: =VLOOKUP(fantasycypherrs[[#This Row],[Cypher Name]],Sheet1!E:O,11,FALSE()) -> Chasseur/Traqueur | F89: =VLOOKUP(fantasycypherrs[[#This Row],[Cypher Name]],Sheet1!E:O,5,FALSE()) -> 1d6 | G89: =VLOOKUP(fantasycypherrs[[#This Row],[Cypher Name]],Sheet1!E:O,2,FALSE()) -> Avec un mouvement à longue portée, ce missile intelligent suit et attaque une cible spécifiée (la cible doit àêtre à la vue lors de la sélection). S'il rate, il continue d'attaquer une fois supplémentaire par niveau de cypher jusqu'à ce qu'il touche. Par exemple, un chasseur/traqueur de niveau 4 attaquera un maximum de cinq fois. Lancez un d100 pour déterminer le type d'attaque.
A90: crystal of strange illusions | C90: image projector | D90: 390 | E90: =VLOOKUP(fantasycypherrs[[#This Row],[Cypher Name]],Sheet1!E:O,11,FALSE()) -> Projecteur d'Image | F90: =VLOOKUP(fantasycypherrs[[#This Row],[Cypher Name]],Sheet1!E:O,5,FALSE()) -> 1d6 | G90: =VLOOKUP(fantasycypherrs[[#This Row],[Cypher Name]],Sheet1!E:O,2,FALSE()) -> Projette l'une des images immobiles suivantes dans la zone décrite pendant une heure. L'image apparaît à une distance proche de l'utilisateur (longue distance si le niveau du cypher est 4 ou plus, très longue distance si le niveau du cypher est 6 ou plus). Les scènes incluent mouvement, son et odeur. Lancez un d100 pour déterminer l'image.
A91: scroll of fiery wall | C91: inferno wall | D91: 390 | E91: =VLOOKUP(fantasycypherrs[[#This Row],[Cypher Name]],Sheet1!E:O,11,FALSE()) -> Mur Infernal | F91: =VLOOKUP(fantasycypherrs[[#This Row],[Cypher Name]],Sheet1!E:O,5,FALSE()) -> 1d6 + 2 | G91: =VLOOKUP(fantasycypherrs[[#This Row],[Cypher Name]],Sheet1!E:O,2,FALSE()) -> Crée un mur de chaleur extràême mesurant jusqu'à 30 pieds par 30 pieds par 1 pied (9 m par 9 m par 30 cm) qui inflige des dégâts égaux au niveau du cypher à tout ce qui passe à travers. Le mur s'adapte à l'espace disponible. Il dure dix minutes.
A92: idol of the housefly spy | C92: infiltrator | D92: 390 | E92: Infiltrateur | F92: =VLOOKUP(fantasycypherrs[[#This Row],[Cypher Name]],Sheet1!E:O,5,FALSE()) -> 1d6 | G92: =VLOOKUP(fantasycypherrs[[#This Row],[Cypher Name]],Sheet1!E:O,2,FALSE()) -> Une petite capsule se lance et se déplace à grande Célérité, cartographiant et scannant une zone inconnue. Elle se déplace de 500 pieds (150 m) par niveau, scannant une zone jusqu'à 50 pieds (15 m) à partir de sa position. Elle identifie la disposition de base, les créatures et les principales sources d'énergie et transmet cette information à l'utilisateur (peut-àêtre par télépathie ou signal électronique) ou revient à l'utilisateur pour montrer ce qu'elle a vu. Son mouvement est bloqué par tout obstacle physique ou énergétique.
A93: potion of snooping | C93: information sensor | D93: 391 | E93: =VLOOKUP(fantasycypherrs[[#This Row],[Cypher Name]],Sheet1!E:O,11,FALSE()) -> Capteur d'Information | F93: =VLOOKUP(fantasycypherrs[[#This Row],[Cypher Name]],Sheet1!E:O,5,FALSE()) -> 1d6 + 2 | G93: =VLOOKUP(fantasycypherrs[[#This Row],[Cypher Name]],Sheet1!E:O,2,FALSE()) -> Au cours d'une journée, l'utilisateur peut activer le cypher un nombre total de fois égal à son niveau. Chaque fois, il peut sélectionner une créature vivante dans un long rayon et apprendre les informations suivantes à son sujet : niveau, origine, espèce, nom, et possiblement d'autres faits (comme le score de crédit d'un individu, son adresse, son numéro de téléphone et des informations connexes).
A94: rune of the servant golem | C94: instant servant | D94: 391 | E94: =VLOOKUP(fantasycypherrs[[#This Row],[Cypher Name]],Sheet1!E:O,11,FALSE()) -> Serviteur Instantané | F94: =VLOOKUP(fantasycypherrs[[#This Row],[Cypher Name]],Sheet1!E:O,5,FALSE()) -> 1d6 | G94: =VLOOKUP(fantasycypherrs[[#This Row],[Cypher Name]],Sheet1!E:O,2,FALSE()) -> Petit appareil s'étend en un automate humanoà¯de d'environ 2 pieds (60 cm) de haut. Son niveau est égal au niveau du cypher, et il peut comprendre les commandes verbales du personnage qui l'a activé. Une fois le serviteur activé, le commandement n'est pas une action. Il peut attaquer ou effectuer des actions comme ordonné au mieux de ses capacités, mais il ne peut pas parler.
A95: scroll of secure shelter | C95: instant shelter | D95: 391 | E95: =VLOOKUP(fantasycypherrs[[#This Row],[Cypher Name]],Sheet1!E:O,11,FALSE()) -> Abri Instantané | F95: =VLOOKUP(fantasycypherrs[[#This Row],[Cypher Name]],Sheet1!E:O,5,FALSE()) -> 1d6 + 3 | G95: =VLOOKUP(fantasycypherrs[[#This Row],[Cypher Name]],Sheet1!E:O,2,FALSE()) -> Avec l'ajout d'eau et d'air, ce cypher s'étend en une simple structure d'une pièce avec une porte et une fenàêtre transparente (deux pièces avec une porte intérieure si le niveau du cypher est 7 ou plus). La structure mesure 10 pieds par 10 pieds par 20 pieds (3 m par 3 m par 6 m). Elle est fabriquée à partir d'un matériau durable et non inflammable similaire au grès, et est permanente et immobile une fois créée.
A96: potion of mental clarity | C96: Intellect booster | D96: 391 | E96: =VLOOKUP(fantasycypherrs[[#This Row],[Cypher Name]],Sheet1!E:O,11,FALSE()) -> Amplificateur d'Intellect | F96: =VLOOKUP(fantasycypherrs[[#This Row],[Cypher Name]],Sheet1!E:O,5,FALSE()) -> 1d6 + 2 | G96: =VLOOKUP(fantasycypherrs[[#This Row],[Cypher Name]],Sheet1!E:O,2,FALSE()) -> Ajoute 1 à l'Avantage d'Intellect de l'utilisateur pendant une heure (ou 2 si le cypher est de niveau 5 ou plus).
A97: potion of sagacious deduction | C97: intelligence enhancement | D97: 391 | E97: =VLOOKUP(fantasycypherrs[[#This Row],[Cypher Name]],Sheet1!E:O,11,FALSE()) -> Amélioration de l'Intelligence | F97: =VLOOKUP(fantasycypherrs[[#This Row],[Cypher Name]],Sheet1!E:O,5,FALSE()) -> 1d6 | G97: =VLOOKUP(fantasycypherrs[[#This Row],[Cypher Name]],Sheet1!E:O,2,FALSE()) -> Toutes les tâches de l'utilisateur impliquant des déductions intelligentes&mdash;comme jouer aux échecs, inférer une connexion entre des indices, résoudre un problème mathématique, trouver un bogue dans le code informatique, et ainsi de suite&mdash;sont facilitées de deux étapes pendant une heure. Au cours de l'heure suivante, la tension entrave les màêmes tâches de deux étapes.
A98: potion of enhanced skill | C98: knowledge enhancement | D98: 391 | E98: =VLOOKUP(fantasycypherrs[[#This Row],[Cypher Name]],Sheet1!E:O,11,FALSE()) -> Amélioration de la Connaissance | F98: =VLOOKUP(fantasycypherrs[[#This Row],[Cypher Name]],Sheet1!E:O,5,FALSE()) -> 1d6 | G98: =VLOOKUP(fantasycypherrs[[#This Row],[Cypher Name]],Sheet1!E:O,2,FALSE()) -> Pour la journée suivante, le personnage reà§oit un entraînement dans une compétence prédéterminée (ou deux compétences si le cypher est de niveau 5 ou plus). La compétence peut àêtre n'importe quoi (y compris quelque chose de spécifique au fonctionnement d'un appareil particulier), ou lancez un d100 pour choisir une compétence commune. (Il est facile de devenir dépendant de l'adrénaline rapide de l'entraînement qu'apportent les cyphers d'amélioration de la connaissance. Les personnages qui s'y fient trop souvent peuvent se retrouver désavantagés lorsqu'ils en manquent, offrant une grande opportunité pour une intrusion du MJ.)
A99: scroll of lightning wall | C99: lightning wall | D99: 391 | E99: =VLOOKUP(fantasycypherrs[[#This Row],[Cypher Name]],Sheet1!E:O,11,FALSE()) -> Mur d'Eclairs | F99: =VLOOKUP(fantasycypherrs[[#This Row],[Cypher Name]],Sheet1!E:O,5,FALSE()) -> 1d6 + 2 | G99: =VLOOKUP(fantasycypherrs[[#This Row],[Cypher Name]],Sheet1!E:O,2,FALSE()) -> Crée un mur de décharges électriques mesurant jusqu'à 30 pieds par 30 pieds par 1 pied (9 m par 9 m par 30 cm) qui inflige des dégâts égaux au niveau du cypher à tout ce qui passe à travers. Le mur s'adapte à l'espace disponible. Il dure dix minutes.
A100: scroll of golem control | C100: machine control | D100: 392 | E100: =VLOOKUP(fantasycypherrs[[#This Row],[Cypher Name]],Sheet1!E:O,11,FALSE()) -> Contrôle de Machine | F100: =VLOOKUP(fantasycypherrs[[#This Row],[Cypher Name]],Sheet1!E:O,5,FALSE()) -> 1d6 + 2 | G100: =VLOOKUP(fantasycypherrs[[#This Row],[Cypher Name]],Sheet1!E:O,2,FALSE()) -> Se divise en deux morceaux ; l'un est fixé à un appareil et l'autre à un personnage. Le personnage peut alors utiliser son esprit pour contrôler l'appareil à longue portée, lui ordonnant de faire tout ce qu'il pourrait faire normalement. Ainsi, un appareil pourrait àêtre activé ou désactivé, et un véhicule pourrait àêtre piloté. Le contrôle dure dix minutes par niveau de cypher, et une fois l'appareil choisi, il ne peut pas àêtre changé.
A101: metal-seeking dart | C101: magnetic attack drill | D101: 392 | E101: =VLOOKUP(fantasycypherrs[[#This Row],[Cypher Name]],Sheet1!E:O,11,FALSE()) -> Foreuse d'Attaque Magnétique | F101: =VLOOKUP(fantasycypherrs[[#This Row],[Cypher Name]],Sheet1!E:O,5,FALSE()) -> 1d6 + 2 | G101: =VLOOKUP(fantasycypherrs[[#This Row],[Cypher Name]],Sheet1!E:O,2,FALSE()) -> L'utilisateur lance ce cypher sur une cible à portée courte, et il s'enfonce dans la cible pendant un tour, infligeant des dégâts égaux au niveau du cypher. Si la cible est en métal ou porte du métal (comme une armure), l'attaque est facilitée.
A102: potion of metal telekinesis | C102: magnetic master | D102: 392 | E102: =VLOOKUP(fantasycypherrs[[#This Row],[Cypher Name]],Sheet1!E:O,11,FALSE()) -> Maître Magnétique | F102: =VLOOKUP(fantasycypherrs[[#This Row],[Cypher Name]],Sheet1!E:O,5,FALSE()) -> 1d6 + 2 | G102: =VLOOKUP(fantasycypherrs[[#This Row],[Cypher Name]],Sheet1!E:O,2,FALSE()) -> Etablit une connexion avec un objet métallique à portée courte qu'un humain pourrait tenir d'une main. L'utilisateur peut ensuite déplacer ou manipuler l'objet n'importe oà¹ dans la portée courte (chaque mouvement ou manipulation est une action). Par exemple, il pourrait manier une arme ou tirer un casque fixé à la tàête d'un ennemi d'avant en arrière. La connexion dure dix tours par niveau de cypher.
A103: potion of metal repulsion | C103: magnetic shield | D103: 392 | E103: =VLOOKUP(fantasycypherrs[[#This Row],[Cypher Name]],Sheet1!E:O,11,FALSE()) -> Bouclier Magnétique | F103: =VLOOKUP(fantasycypherrs[[#This Row],[Cypher Name]],Sheet1!E:O,5,FALSE()) -> 1d6 + 2 | G103: =VLOOKUP(fantasycypherrs[[#This Row],[Cypher Name]],Sheet1!E:O,2,FALSE()) -> Pendant dix minutes par niveau de cypher, les objets métalliques ne peuvent pas se trouver à portée immédiate de l'utilisateur. Les objets métalliques déjà dans la zone lorsque le dispositif est activé sont lentement repoussés.
A104: potion of mage hand | C104: manipulation beam | D104: 392 | E104: =VLOOKUP(fantasycypherrs[[#This Row],[Cypher Name]],Sheet1!E:O,11,FALSE()) -> Faisceau de Manipulation | F104: =VLOOKUP(fantasycypherrs[[#This Row],[Cypher Name]],Sheet1!E:O,5,FALSE()) -> 1d6 + 2 | G104: =VLOOKUP(fantasycypherrs[[#This Row],[Cypher Name]],Sheet1!E:O,2,FALSE()) -> Au cours d'une journée, l'utilisateur peut activer le cypher un nombre total de fois égal à son niveau. Chaque fois, il peut affecter un objet qu'il peut voir à longue portée qui n'est pas trop lourd pour lui à manipuler physiquement. L'effet doit se produire au cours d'un tour et pourrait inclure la fermeture ou l'ouverture d'une porte, la saisie d'un numéro sur un clavier, le transfert d'un objet sur une courte distance, le fait de retirer un objet des mains d'une autre créature (avec un jet réussi basé sur la Puissance), ou de pousser une créature sur une distance immédiate. (Un faisceau de manipulation pourrait àêtre utilisé pour faire fonctionner un ordinateur à distance, ce qui faciliterait certaines missions d'infiltration et de piratage.)
A105: scroll of object teleportation | C105: matter transference ray | D105: 392 | E105: =VLOOKUP(fantasycypherrs[[#This Row],[Cypher Name]],Sheet1!E:O,11,FALSE()) -> Rayon de Transfert de Matière | F105: =VLOOKUP(fantasycypherrs[[#This Row],[Cypher Name]],Sheet1!E:O,5,FALSE()) -> 1d6 + 3 | G105: =VLOOKUP(fantasycypherrs[[#This Row],[Cypher Name]],Sheet1!E:O,2,FALSE()) -> L'utilisateur peut cibler un objet non vivant à longue portée qui est de sa taille ou plus petit, de niveau de cypher égal ou inférieur. L'objet est transféré directement à un emplacement aléatoire situé à au moins 100 miles (160 km) de distance. Si La Meneuse estime que cela est approprié aux circonstances, seule une partie d'un objet est transférée (une partie dont le volume n'est pas supérieur à celui de l'utilisateur).
A106: potion of meditation | C106: meditation aid (level 3–4) | D106: 392 | E106: Aide à la Méditation (niveau 3-4) | F106: 1d6 + 2 | G106: Restaure un nombre de points égal au niveau du cypher à la Réserve d'Intellect de l'utilisateur.
A107: potion of greater meditation | C107: meditation aid (level 5–6) | D107: 392 | E107: Aide à la Méditation (niveau 5-6) | F107: 1d6 + 2 | G107: Restaure un nombre de points égal au niveau du cypher à la Réserve d'Intellect de l'utilisateur.
...

Sheet Sheet1
A1: pub_date | B1: created | C1: updated | D1: name | E1: name_en | F1: effect | G1: hint | H1: table | I1: level | J1: cs_page | K1: is_manifeste | L1: is_fantastic | M1: is_subtle | N1: Column1 | O1: Column2
A2: 2024-10-01T16:53:31.844Z | B2: 2024-10-01T16:53:31.844Z | C2: 2024-10-01T16:53:31.844Z | D2: Stimulant | E2: Stim | F2: Facilite la prochaine action de l'utilisateur de trois crans. | I2: 1d6 | J2: (Cypher System Rulebook, page 398) | K2: =FALSE() -> FALSE | L2: =FALSE() -> FALSE | M2: =TRUE() -> TRUE | N2: =LEN(Table1[[#This Row],[effect]]) -> 61 | O2: =Table1[[#This Row],[name]] -> Stimulant
A3: 2024-10-01T16:53:31.483Z | B3: 2024-10-01T16:53:31.483Z | C3: 2024-10-01T16:53:31.483Z | D3: Stabilisateur Mental | E3: Mind Stabilizer | F3: L'utilisateur gagne +5 à l'Armure contre les dégâts d'Intellect. | I3: 1d6 | J3: (Cypher System Rulebook, page 393) | K3: =FALSE() -> FALSE | L3: =FALSE() -> FALSE | M3: =TRUE() -> TRUE | N3: =LEN(Table1[[#This Row],[effect]]) -> 65 | O3: =Table1[[#This Row],[name]] -> Stabilisateur Mental
A4: 2024-10-01T16:53:30.915Z | B4: 2024-10-01T16:53:30.915Z | C4: 2024-10-01T16:53:30.915Z | D4: Catholicon | E4: Catholicon | F4: Guérit toute maladie d'un niveau égal ou inférieur à celui du cypher. | I4: 1d6 + 2 | J4: (Cypher System Rulebook, page 385) | K4: =TRUE() -> TRUE | L4: =FALSE() -> FALSE | M4: =FALSE() -> FALSE | N4: =LEN(Table1[[#This Row],[effect]]) -> 70 | O4: =Table1[[#This Row],[name]] -> Catholicon
A5: 2024-10-01T16:53:31.528Z | B5: 2024-10-01T16:53:31.528Z | C5: 2024-10-01T16:53:31.528Z | D5: Perfection | E5: Perfection | F5: L'utilisateur considère sa prochaine action comme s'il avait lancé un naturel 20. | I5: 1d6 + 2 | J5: (Cypher System Rulebook, page 393) | K5: =TRUE() -> TRUE | L5: =FALSE() -> FALSE | M5: =TRUE() -> TRUE | N5: =LEN(Table1[[#This Row],[effect]]) -> 81 | O5: =Table1[[#This Row],[name]] -> Perfection
A6: 2024-10-01T16:53:31.676Z | B6: 2024-10-01T16:53:31.676Z | C6: 2024-10-01T16:53:31.676Z | D6: Régénérateur | E6: Rejuvenator | F6: Restaure un nombre de points égal au niveau du cypher à une Réserve de stat aléatoire. | H6: <table class="table table-light table-striped table-sm og-dt"> <thead> <tr> <th scope="col" class="text-center w-15">d100</th> <th>Stat Pool</th> </tr> </thead> <tbody> <tr> <td scope="col" class="text-center w-15">01&mdash;50</td> <td>Réserve de Puissance</td> </tr> <tr> <td scope="col" class="text-center w-15">51&mdash;75</td> <td>Réserve de Célérité</td> </tr> <tr> <td scope="col" class="text-center w-15">76&mdash;00</td> <td>Réserve d'Intellect</td> </tr> </tbody> </table> | I6: 1d6 + 2 | J6: (Cypher System Rulebook, page 395) | K6: =FALSE() -> FALSE | L6: =FALSE() -> FALSE | M6: =TRUE() -> TRUE | N6: =LEN(Table1[[#This Row],[effect]]) -> 87 | O6: =Table1[[#This Row],[name]] -> Régénérateur
A7: 2024-10-01T16:53:31.429Z | B7: 2024-10-01T16:53:31.429Z | C7: 2024-10-01T16:53:31.429Z | D7: Aide à la Méditation | E7: Meditation Aid | F7: Restaure un nombre de points égal au niveau du cypher à la Réserve d'Intellect de l'utilisateur. | I7: 1d6 + 2 | J7: (Cypher System Rulebook, page 392) | K7: =FALSE() -> FALSE | L7: =FALSE() -> FALSE | M7: =TRUE() -> TRUE | N7: =LEN(Table1[[#This Row],[effect]]) -> 97 | O7: =Table1[[#This Row],[name]] -> Aide à la Méditation
A8: 2024-10-01T16:53:32.019Z | B8: 2024-10-01T16:53:32.019Z | C8: 2024-10-01T16:53:32.019Z | D8: Ailes | E8: Wings | F8: L'utilisateur peut voler à sa vitesse de course normale pendant dix minutes par niveau de cypher. | I8: 1d6 + 2 | J8: (Cypher System Rulebook, page 400) | K8: =TRUE() -> TRUE | L8: =TRUE() -> TRUE | M8: =FALSE() -> FALSE | N8: =LEN(Table1[[#This Row],[effect]]) -> 98 | O8: =Table1[[#This Row],[name]] -> Ailes
A9: 2024-10-01T16:53:30.845Z | B9: 2024-10-01T16:53:30.845Z | C9: 2024-10-01T16:53:30.845Z | D9: Analeptique | E9: Analeptic | F9: Restaure un nombre de points égal au niveau du cypher dans la Réserve de Célérité de l'utilisateur. | I9: 1d6 + 2 | J9: (Cypher System Rulebook, page 384) | K9: =FALSE() -> FALSE | L9: =FALSE() -> FALSE | M9: =TRUE() -> TRUE | N9: =LEN(Table1[[#This Row],[effect]]) -> 99 | O9: =Table1[[#This Row],[name]] -> Analeptique
A10: 2024-10-01T16:53:31.169Z | B10: 2024-10-01T16:53:31.169Z | C10: 2024-10-01T16:53:31.169Z | D10: Bouclier Durable | E10: Enduring Shield | F10: Pour la prochaine journée, l'utilisateur bénéficie d'un atout pour les jets de défense en Célérité. | I10: 1d6 + 4 | J10: (Cypher System Rulebook, page 388) | K10: =FALSE() -> FALSE | L10: =FALSE() -> FALSE | M10: =TRUE() -> TRUE | N10: =LEN(Table1[[#This Row],[effect]]) -> 99 | O10: =Table1[[#This Row],[name]] -> Bouclier Durable
A11: 2024-10-01T16:53:30.959Z | B11: 2024-10-01T16:53:30.959Z | C11: 2024-10-01T16:53:30.959Z | D11: Curatif | E11: Curative | F11: Restaure un nombre de points égal au niveau du cypher dans la Réserve de Puissance de l'utilisateur. | I11: 1d6 + 2 | J11: (Cypher System Rulebook, page 386) | K11: =TRUE() -> TRUE | L11: =FALSE() -> FALSE | M11: =TRUE() -> TRUE | N11: =LEN(Table1[[#This Row],[effect]]) -> 100 | O11: =Table1[[#This Row],[name]] -> Curatif
A12: 2024-10-01T16:53:31.547Z | B12: 2024-10-01T16:53:31.547Z | C12: 2024-10-01T16:53:31.547Z | D12: Poison (Emotion) | E12: Poison (Emotion) | F12: La victime ressent une émotion spécifique pendant une heure. Lancez un d100 pour déterminer l'émotion. | G12: ===== <table class="table table-light table-striped table-sm og-dt"> <thead> <tr> <th scope="col" class="text-center w-15">d100</th> <th>Emotion</th> </tr> </thead> <tbody> <tr> <td scope="col" class="text-center w-15">01&mdash;20</td> <td>Colère. Pràêt à attaquer quiconque n'est pas d'accord avec eux. Très difficile à interagir ; toutes ces actions sont entravées de deux étapes.</td> </tr> <tr> <td scope="col" class="text-center w-15">21&mdash;40</td> <td>Peur. Fuit dans la terreur pendant une minute lorsqu'il est menacé.</td> </tr> <tr> <td scope="col" class="text-center w-15">41&mdash;60</td> <td>Désir. Ne peut se concentrer sur aucune activité non sexuelle.</td> </tr> <tr> <td scope="col" class="text-center w-15">61&mdash;75</td> <td>Tristesse. Toutes les tâches sont entravées.</td> </tr> <tr> <td scope="col" class="text-center w-15">76&mdash;85</td> <td>Complaisance. N'a aucune motivation. Toutes les tâches sont entravées de deux étapes.</td> </tr> <tr> <td scope="col" class="text-center w-15">86&mdash;95</td> <td>Joie. Facile à interagir de manière agréable ; toutes les tâches d'interaction agréables sont facilitées.</td> </tr> <tr> <td scope="col" class="text-center w-15">96&mdash;00</td> <td>Amour. Beaucoup plus facile à interagir ; toutes les tâches d'interaction sont facilitées de deux étapes, mais un attachement temporaire est probable.</td> </tr> </tbody> </table> ===== | H12: <table class="table table-light table-striped table-sm og-dt"> <thead> <tr> <th scope="col" class="text-center w-15">d100</th> <th>Emotion</th> </tr> </thead> <tbody> <tr> <td scope="col" class="text-center w-15">01&mdash;20</td> <td>Colère. Pràêt à attaquer quiconque n'est pas d'accord avec eux. Très difficile à interagir ; toutes ces actions sont entravées de deux étapes.</td> </tr> <tr> <td scope="col" class="text-center w-15">21&mdash;40</td> <td>Peur. Fuit dans la terreur pendant une minute lorsqu'il est menacé.</td> </tr> <tr> <td scope="col" class="text-center w-15">41&mdash;60</td> <td>Désir. Ne peut se concentrer sur aucune activité non sexuelle.</td> </tr> <tr> <td scope="col" class="text-center w-15">61&mdash;75</td> <td>Tristesse. Toutes les tâches sont entravées.</td> </tr> <tr> <td scope="col" class="text-center w-15">76&mdash;85</td> <td>Complaisance. N'a aucune motivation. Toutes les tâches sont entravées de deux étapes.</td> </tr> <tr> <td scope="col" class="text-center w-15">86&mdash;95</td> <td>Joie. Facile à interagir de manière agréable ; toutes les tâches d'interaction agréables sont facilitées.</td> </tr> <tr> <td scope="col" class="text-center w-15">96&mdash;00</td> <td>Amour. Beaucoup plus facile à interagir ; toutes les tâches d'interaction sont facilitées de deux étapes, mais un attachement temporaire est probable.</td> </tr> </tbody> </table> | I12: 1d6 + 2 | J12: (Cypher System Rulebook, page 394) | K12: =TRUE() -> TRUE | L12: =FALSE() -> FALSE | M12: =FALSE() -> FALSE | N12: =LEN(Table1[[#This Row],[effect]]) -> 102 | O12: =Table1[[#This Row],[name]] -> Poison (Emotion)
A13: 2024-10-01T16:53:31.851Z | B13: 2024-10-01T16:53:31.851Z | C13: 2024-10-01T16:53:31.851Z | D13: Amélioration de Puissance | E13: Strength Boost | F13: Ajoute 1 à l'Avantage de Puissance pendant une heure (ou 2 si le cypher est de niveau 5 ou supérieur). | I13: 1d6 + 2 | J13: (Cypher System Rulebook, page 398) | K13: =FALSE() -> FALSE | L13: =FALSE() -> FALSE | M13: =TRUE() -> TRUE | N13: =LEN(Table1[[#This Row],[effect]]) -> 103 | O13: =Table1[[#This Row],[name]] -> Amélioration de Puissance
A14: 2024-10-01T16:53:31.107Z | B14: 2024-10-01T16:53:31.107Z | C14: 2024-10-01T16:53:31.107Z | D14: Désarmement | E14: Disarm | F14: Un PNJ dans un rayon immédiat dont le niveau est inférieur à celui du cypher laisse tomber ce qu'il tient. | I14: 1d6 + 1 | J14: (Cypher System Rulebook, page 387) | K14: =FALSE() -> FALSE | L14: =FALSE() -> FALSE | M14: =TRUE() -> TRUE | N14: =LEN(Table1[[#This Row],[effect]]) -> 107 | O14: =Table1[[#This Row],[name]] -> Désarmement
A15: 2024-10-01T16:53:31.792Z | B15: 2024-10-01T16:53:31.792Z | C15: 2024-10-01T16:53:31.792Z | D15: Solvant | E15: Solvent | F15: Dissout 1 pied cube de matériel chaque round. Après un round par niveau de cypher, le cypher devient inerte. | I15: 1d10 | J15: (Cypher System Rulebook, page 397) | K15: =TRUE() -> TRUE | L15: =FALSE() -> FALSE | M15: =FALSE() -> FALSE | N15: =LEN(Table1[[#This Row],[effect]]) -> 108 | O15: =Table1[[#This Row],[name]] -> Solvant
A16: 2024-10-01T16:53:31.348Z | B16: 2024-10-01T16:53:31.348Z | C16: 2024-10-01T16:53:31.348Z | D16: Amplificateur d'Intellect | E16: Intellect Booster | F16: Ajoute 1 à l'Avantage d'Intellect de l'utilisateur pendant une heure (ou 2 si le cypher est de niveau 5 ou plus). | I16: 1d6 + 2 | J16: (Cypher System Rulebook, page 391) | K16: =FALSE() -> FALSE | L16: =FALSE() -> FALSE | M16: =TRUE() -> TRUE | N16: =LEN(Table1[[#This Row],[effect]]) -> 114 | O16: =Table1[[#This Row],[name]] -> Amplificateur d'Intellect
A17: 2024-10-01T16:53:30.860Z | B17: 2024-10-01T16:53:30.860Z | C17: 2024-10-01T16:53:30.860Z | D17: Renforcement d'Armure | E17: Armor Reinforcer | F17: armure de l'utilisateur bénéficie d'une amélioration pendant vingt-quatre heures. Lancez un d6 pour déterminer le résultat. | H17: <table class="table table-light table-striped table-sm og-dt"> <thead> <tr> <th>d6</th> <th>Bonus d'Armure</th> </tr> </thead> <tbody> <tr> <td scope="col" class="text-center w-15">1</td> <td>+1 à l'Armure</td> </tr> <tr> <td scope="col" class="text-center w-15">2</td> <td>+2 à l'Armure</td> </tr> <tr> <td scope="col" class="text-center w-15">3</td> <td>+3 à l'Armure</td> </tr> <tr> <td scope="col" class="text-center w-15">4</td> <td>+2 à l'Armure, +5 contre les dégâts de feu</td> </tr> <tr> <td scope="col" class="text-center w-15">5</td> <td>+2 à l'Armure, +5 contre les dégâts de froid</td> </tr> <tr> <td scope="col" class="text-center w-15">6</td> <td>+2 à l'Armure, +5 contre les dégâts d'acide</td> </tr> </tbody> </table> | I17: 1d6 + 1 | J17: (Cypher System Rulebook, page 384) | K17: =TRUE() -> TRUE | L17: =FALSE() -> FALSE | M17: =FALSE() -> FALSE | N17: =LEN(Table1[[#This Row],[effect]]) -> 123 | O17: =Table1[[#This Row],[name]] -> Renforcement d'Armure
A18: 2024-10-01T16:53:30.835Z | B18: 2024-10-01T16:53:30.835Z | C18: 2024-10-01T16:53:30.835Z | D18: Adhésion | E18: Adhesion | F18: Permet de grimper automatiquement sur toute les surfaces, màême horizontales. Dure pendant 10 minutes par niveau du cypher. | I18: 1d6 | J18: (Cypher System Rulebook, page 384) | K18: =TRUE() -> TRUE | L18: =FALSE() -> FALSE | M18: =FALSE() -> FALSE | N18: =LEN(Table1[[#This Row],[effect]]) -> 123 | O18: =Table1[[#This Row],[name]] -> Adhésion
A19: 2024-10-01T16:53:31.821Z | B19: 2024-10-01T16:53:31.821Z | C19: 2024-10-01T16:53:31.821Z | D19: Amélioration de Célérité | E19: Speed Boost | F19: Ajoute 1 à l'Avantage de Célérité de l'utilisateur pendant une heure (ajoute 2 si le cypher est de niveau 5 ou supérieur). | I19: 1d6 + 2 | J19: (Cypher System Rulebook, page 398) | K19: =FALSE() -> FALSE | L19: =FALSE() -> FALSE | M19: =FALSE() -> FALSE | N19: =LEN(Table1[[#This Row],[effect]]) -> 123 | O19: =Table1[[#This Row],[name]] -> Amélioration de Célérité
A20: 2024-10-01T16:53:31.518Z | B20: 2024-10-01T16:53:31.518Z | C20: 2024-10-01T16:53:31.518Z | D20: Nutrition et Hydratation | E20: Nutrition And Hydration | F20: L'utilisateur peut se passer de nourriture et d'eau pendant un nombre de jours égal au niveau du cypher sans effets néfastes. | I20: 1d6 + 1 | J20: (Cypher System Rulebook, page 393) | K20: =FALSE() -> FALSE | L20: =FALSE() -> FALSE | M20: =TRUE() -> TRUE | N20: =LEN(Table1[[#This Row],[effect]]) -> 125 | O20: =Table1[[#This Row],[name]] -> Nutrition et Hydratation
A21: 2024-10-01T16:53:31.753Z | B21: 2024-10-01T16:53:31.753Z | C21: 2024-10-01T16:53:31.753Z | D21: Electrisant | E21: Shocker | F21: Inflige une puissante décharge d'électricité qui choque toute créature touchée, infligeant des dégâts égaux au niveau du cyphe | I21: 1d6 + 4 | J21: (Cypher System Rulebook, page 396) | K21: =TRUE() -> TRUE | L21: =FALSE() -> FALSE | M21: =FALSE() -> FALSE | N21: =LEN(Table1[[#This Row],[effect]]) -> 126 | O21: =Table1[[#This Row],[name]] -> Electrisant
A22: 2024-10-01T16:53:31.876Z | B22: 2024-10-01T16:53:31.876Z | C22: 2024-10-01T16:53:31.876Z | D22: Télépathie | E22: Telepathy | F22: Pendant une heure, le dispositif permet une communication mentale à longue distance avec quiconque que l'utilisateur peut voir. | I22: 1d6 + 2 | J22: (Cypher System Rulebook, page 398) | K22: =TRUE() -> TRUE | L22: =TRUE() -> TRUE | M22: =FALSE() -> FALSE | N22: =LEN(Table1[[#This Row],[effect]]) -> 128 | O22: =Table1[[#This Row],[name]] -> Télépathie
A23: 2024-10-01T16:53:31.564Z | B23: 2024-10-01T16:53:31.564Z | C23: 2024-10-01T16:53:31.564Z | D23: Poison (Contrôle Mental) | E23: Poison (Mind Controlling) | F23: La victime doit accomplir une action spécifique en réponse à un déclencheur spécifique. Lancez un d100 pour déterminer l'action. | H23: <table class="table table-light table-striped table-sm og-dt"> <thead> <tr> <th scope="col" class="text-center w-15">d100</th> <th>Action</th> </tr> </thead> <tbody> <tr> <td scope="col" class="text-center w-15">01&mdash;20</td> <td>Se couche pendant une minute les yeux fermés lorsqu'on lui demande.</td> </tr> <tr> <td scope="col" class="text-center w-15">21&mdash;40</td> <td>Fuit dans la terreur pendant une minute lorsqu'elle est menacée.</td> </tr> <tr> <td scope="col" class="text-center w-15">41&mdash;60</td> <td>Répond aux questions honnàêtement pendant une minute.</td> </tr> <tr> <td scope="col" class="text-center w-15">61&mdash;75</td> <td>Attaque un ami proche pendant un round lorsqu'il est à portée immédiate.</td> </tr> <tr> <td scope="col" class="text-center w-15">76&mdash;85</td> <td>Obéit à la prochaine commande verbale donnée (si elle est comprise).</td> </tr> <tr> <td scope="col" class="text-center w-15">86&mdash;95</td> <td>Pendant un jour, devient sexuellement attiré par la prochaine créature de sa propre espèce qu'il voit.</td> </tr> <tr> <td scope="col" class="text-center w-15">96&mdash;00</td> <td>Pendant une minute, se dirige vers le prochain objet rouge aperà§u au lieu de toutes les autres actions, ignorant l'autoconservation.</td> </tr> </tbody> </table> | I23: 1d6 + 2 | J23: (Cypher System Rulebook, page 394) | K23: =TRUE() -> TRUE | L23: =TRUE() -> TRUE | M23: =FALSE() -> FALSE | N23: =LEN(Table1[[#This Row],[effect]]) -> 129 | O23: =Table1[[#This Row],[name]] -> Poison (Contrôle Mental)
A24: 2024-10-01T16:53:31.190Z | B24: 2024-10-01T16:53:31.190Z | C24: 2024-10-01T16:53:31.190Z | D24: Résistance au Feu | E24: Fireproofing | F24: Un objet inanimé traité par ce cypher bénéficie d'une Armure contre les dégâts de feu égale au niveau du cypher pendant une journée. | I24: 1d6 + 4 | J24: (Cypher System Rulebook, page 388) | K24: =TRUE() -> TRUE | L24: =FALSE() -> FALSE | M24: =FALSE() -> FALSE | N24: =LEN(Table1[[#This Row],[effect]]) -> 132 | O24: =Table1[[#This Row],[name]] -> Résistance au Feu
A25: 2024-10-01T16:53:32.010Z | B25: 2024-10-01T16:53:32.010Z | C25: 2024-10-01T16:53:32.010Z | D25: Amélioration d'Arme | E25: Weapon Enhancement | F25: Modifie l'attaque d'une arme d'une manière particulière pendant dix minutes par niveau de cypher. Lancez un d100 pour la modification. | H25: <table class="table table-light table-striped table-sm og-dt"> <thead> <tr> <th scope="col" class="text-center w-15">d100</th> <th>Modification</th> </tr> </thead> <tbody> <tr> <td scope="col" class="text-center w-15">01&mdash;10</td> <td>Facilite l'attaque d'un niveau</td> </tr> <tr> <td scope="col" class="text-center w-15">11&mdash;20</td> <td>Inflige des dégâts électriques supplémentaires égaux au niveau du cypher</td> </tr> <tr> <td scope="col" class="text-center w-15">21&mdash;30</td> <td>Inflige des dégâts de froid supplémentaires égaux au niveau du cypher</td> </tr> <tr> <td scope="col" class="text-center w-15">31&mdash;40</td> <td>Inflige des dégâts de poison supplémentaires égaux au niveau du cypher</td> </tr> <tr> <td scope="col" class="text-center w-15">41&mdash;50</td> <td>Inflige des dégâts acides supplémentaires égaux au niveau du cypher</td> </tr> <tr> <td scope="col" class="text-center w-15">51&mdash;60</td> <td>Inflige des dégâts de feu supplémentaires égaux au niveau du cypher</td> </tr> <tr> <td scope="col" class="text-center w-15">61&mdash;70</td> <td>Inflige des dégâts soniques supplémentaires égaux au niveau du cypher</td> </tr> <tr> <td scope="col" class="text-center w-15">71&mdash;80</td> <td>Inflige des dégâts psychiques supplémentaires égaux au niveau du cypher</td> </tr> <tr> <td scope="col" class="text-center w-15">81&mdash;90</td> <td>Recul (sur 18&mdash;20 lors d'un jet d'attaque réussi, la cible est repoussée de 30 pieds [9 m])</td> </tr> <tr> <td scope="col" class="text-center w-15">91&mdash;95</td> <td>Immobilisation (sur 18&mdash;20 lors d'un jet d'attaque réussi, la cible ne peut pas agir lors de son prochain tour)</td> </tr> <tr> <td scope="col" class="text-center w-15">96&mdash;97</td> <td>Facilite l'attaque de deux niveaux</td> </tr> <tr> <td scope="col" class="text-center w-15">98</td> <td>Exil (sur 18&mdash;20 lors d'un jet d'attaque réussi, la cible est envoyée à un endroit aléatoire à au moins 100 miles [160 km] de distance)</td> </tr> <tr> <td scope="col" class="text-center w-15">99</td> <td>Explose, infligeant des dégâts égaux au niveau du cypher à tous ceux dans la portée immédiate</td> </tr> <tr> <td scope="col" class="text-center w-15">00</td> <td>Ciblage du cÅ“ur (sur 18&mdash;20 lors d'un jet d'attaque réussi, la cible est tuée)</td> </tr> </tbody> </table> | I25: 1d6 + 2 | J25: (Cypher System Rulebook, page 400) | K25: =TRUE() -> TRUE | L25: =TRUE() -> TRUE | M25: =FALSE() -> FALSE | N25: =LEN(Table1[[#This Row],[effect]]) -> 134 | O25: =Table1[[#This Row],[name]] -> Amélioration d'Arme
A26: 2024-10-01T16:53:30.882Z | B26: 2024-10-01T16:53:30.882Z | C26: 2024-10-01T16:53:30.882Z | D26: Meilleur Outil | E26: Best Tool | F26: Fournit un atout supplémentaire pour toute tâche utilisant un outil, màême si cela signifie dépasser la limite normale de deux atouts. | I26: 1d6 | J26: (Cypher System Rulebook, page 384) | K26: =FALSE() -> FALSE | L26: =FALSE() -> FALSE | M26: =TRUE() -> TRUE | N26: =LEN(Table1[[#This Row],[effect]]) -> 134 | O26: =Table1[[#This Row],[name]] -> Meilleur Outil
A27: 2024-10-01T16:53:31.985Z | B27: 2024-10-01T16:53:31.985Z | C27: 2024-10-01T16:53:31.985Z | D27: Traducteur Vocal | E27: Vocal Translator | F27: Pendant vingt-quatre heures par niveau de cypher, traduit tout ce que dit l'utilisateur dans une langue que tout le monde peut comprendre. | I27: 1d6 | J27: (Cypher System Rulebook, page 399) | K27: =TRUE() -> TRUE | L27: =TRUE() -> TRUE | M27: =FALSE() -> FALSE | N27: =LEN(Table1[[#This Row],[effect]]) -> 138 | O27: =Table1[[#This Row],[name]] -> Traducteur Vocal
A28: 2024-10-01T16:53:31.658Z | B28: 2024-10-01T16:53:31.658Z | C28: 2024-10-01T16:53:31.658Z | D28: Pic de Réalité | E28: Reality Spike | F28: Une fois activé, le cypher ne bouge jamais, màême s'il est activé en l'air. Une action de Puissance le délogera, mais il sera alors ruiné. | I28: 1d6 + 4 | J28: (Cypher System Rulebook, page 395) | K28: =TRUE() -> TRUE | L28: =TRUE() -> TRUE | M28: =FALSE() -> FALSE | N28: =LEN(Table1[[#This Row],[effect]]) -> 138 | O28: =Table1[[#This Row],[name]] -> Pic de Réalité
A29: 2024-10-01T16:53:31.574Z | B29: 2024-10-01T16:53:31.574Z | C29: 2024-10-01T16:53:31.574Z | D29: Poison (Perturbation Mentale) | E29: Poison (Mind Disrupting) | F29: La victime subit des dégâts d'Intellect égaux au niveau du cypher et ne peut pas agir pendant un nombre de rounds égal au niveau du cypher. | I29: 1d6 + 2 | J29: (Cypher System Rulebook, page 394) | K29: =TRUE() -> TRUE | L29: =FALSE() -> FALSE | M29: =FALSE() -> FALSE | N29: =LEN(Table1[[#This Row],[effect]]) -> 139 | O29: =Table1[[#This Row],[name]] -> Poison (Perturbation Mentale)
A30: 2024-10-01T16:53:31.584Z | B30: 2024-10-01T16:53:31.584Z | C30: 2024-10-01T16:53:31.584Z | D30: Pic de Radiation | E30: Radiation Spike | F30: Inflige une forte impulsion de radiation qui perturbe les tissus de toute créature touchée, infligeant des dégâts égaux au niveau du cypher. | I30: 1d6 + 4 | J30: (Cypher System Rulebook, page 395) | K30: =TRUE() -> TRUE | L30: =FALSE() -> FALSE | M30: =FALSE() -> FALSE | N30: =LEN(Table1[[#This Row],[effect]]) -> 140 | O30: =Table1[[#This Row],[name]] -> Pic de Radiation
A31: 2024-10-01T16:53:31.714Z | B31: 2024-10-01T16:53:31.714Z | C31: 2024-10-01T16:53:31.714Z | D31: Repousser | E31: Repel | F31: Un PNJ à portée immédiate qui est d'un niveau inférieur au cypher décide de partir, utilisant ses cinq prochains rounds pour s'éloigner rapidement. | I31: 1d6 + 1 | J31: (Cypher System Rulebook, page 396) | K31: =FALSE() -> FALSE | L31: =FALSE() -> FALSE | M31: =TRUE() -> TRUE | N31: =LEN(Table1[[#This Row],[effect]]) -> 148 | O31: =Table1[[#This Row],[name]] -> Repousser
A32: 2024-10-01T16:53:31.692Z | B32: 2024-10-01T16:53:31.692Z | C32: 2024-10-01T16:53:31.692Z | D32: Vision à Distance | E32: Remote Viewer | F32: Pendant une heure par niveau de cypher, l'utilisateur peut voir tout ce qui se passe dans les environs du cypher, quelle que soit la distance entre eux. | I32: 1d6 | J32: (Cypher System Rulebook, page 396) | K32: =TRUE() -> TRUE | L32: =FALSE() -> FALSE | M32: =FALSE() -> FALSE | N32: =LEN(Table1[[#This Row],[effect]]) -> 152 | O32: =Table1[[#This Row],[name]] -> Vision à Distance
A33: 2024-10-01T16:53:31.220Z | B33: 2024-10-01T16:53:31.220Z | C33: 2024-10-01T16:53:31.220Z | D33: Projecteur d'Ecran de Force | E33: Force Screen Projector | F33: Crée un plan immobile de force solide mesurant jusqu'à 6 m par 6 m (20 pieds par 20 pieds) pendant une heure. Le plan se conforme à l'espace disponible. | I33: 1d6 + 3 | J33: (Cypher System Rulebook, page 389) | K33: =TRUE() -> TRUE | L33: =TRUE() -> TRUE | M33: =FALSE() -> FALSE | N33: =LEN(Table1[[#This Row],[effect]]) -> 154 | O33: =Table1[[#This Row],[name]] -> Projecteur d'Ecran de Force
A34: 2024-10-01T16:53:31.511Z | B34: 2024-10-01T16:53:31.511Z | C34: 2024-10-01T16:53:31.511Z | D34: Rayon de Nullification | E34: Nullification Ray | F34: L'utilisateur peut mettre immédiatement fin à un effet en cours dans la portée longue qui est produit par un artefact, un cypher ou une capacité spéciale. | I34: 1d6 + 3 | J34: (Cypher System Rulebook, page 393) | K34: =TRUE() -> TRUE | L34: =FALSE() -> FALSE | M34: =FALSE() -> FALSE | N34: =LEN(Table1[[#This Row],[effect]]) -> 155 | O34: =Table1[[#This Row],[name]] -> Rayon de Nullification
A35: 2024-10-01T16:53:30.907Z | B35: 2024-10-01T16:53:30.907Z | C35: 2024-10-01T16:53:30.907Z | D35: Explosion de Célérité | E35: Burst Of Speed | F35: Pendant une minute, un utilisateur qui peut normalement se déplacer sur une courte distance en une action peut se déplacer sur une longue distance à la place. | I35: 1d6 | J35: (Cypher System Rulebook, page 385) | K35: =FALSE() -> FALSE | L35: =FALSE() -> FALSE | M35: =TRUE() -> TRUE | N35: =LEN(Table1[[#This Row],[effect]]) -> 159 | O35: =Table1[[#This Row],[name]] -> Explosion de Célérité
A36: 2024-10-01T16:53:31.040Z | B36: 2024-10-01T16:53:31.040Z | C36: 2024-10-01T16:53:31.040Z | D36: Détonation (Inversion Gravitationnelle) | E36: Detonation (Gravity Inversion) | F36: Projette un petit explosif physique jusqu'à longue distance qui explose, et pendant une heure, la gravité est inversée dans un rayon long autour de l'explosion. | I36: 1d6 + 1 | J36: (Cypher System Rulebook, page 387) | K36: =TRUE() -> TRUE | L36: =TRUE() -> TRUE | M36: =FALSE() -> FALSE | N36: =LEN(Table1[[#This Row],[effect]]) -> 161 | O36: =Table1[[#This Row],[name]] -> Détonation (Inversion Gravitationnelle)
A37: 2024-10-01T16:53:31.776Z | B37: 2024-10-01T16:53:31.776Z | C37: 2024-10-01T16:53:31.776Z | D37: Inducteur de Sommeil | E37: Sleep Inducer | F37: Un contact endort la victime pendant dix minutes par niveau de cypher ou jusqu'à ce qu'elle soit réveillée par une action violente ou un bruit extràêmement fort. | I37: 1d6 | J37: (Cypher System Rulebook, page 397) | K37: =TRUE() -> TRUE | L37: =FALSE() -> FALSE | M37: =FALSE() -> FALSE | N37: =LEN(Table1[[#This Row],[effect]]) -> 162 | O37: =Table1[[#This Row],[name]] -> Inducteur de Sommeil
A38: 2024-10-01T16:53:31.799Z | B38: 2024-10-01T16:53:31.799Z | C38: 2024-10-01T16:53:31.799Z | D38: Trou Sonore | E38: Sonic Hole | F38: Attire tout le son dans un rayon de longue portée dans le dispositif pendant un round par niveau de cypher. Dans la zone affectée, aucun son ne peut àêtre entendu. | I38: 1d6 + 2 | J38: (Cypher System Rulebook, page 397) | K38: =TRUE() -> TRUE | L38: =TRUE() -> TRUE | M38: =FALSE() -> FALSE | N38: =LEN(Table1[[#This Row],[effect]]) -> 163 | O38: =Table1[[#This Row],[name]] -> Trou Sonore
A39: 2024-10-01T16:53:31.213Z | B39: 2024-10-01T16:53:31.213Z | C39: 2024-10-01T16:53:31.213Z | D39: Champ de Force | E39: Force Field | F39: Pour la prochaine journée, l'utilisateur est entouré d'un puissant champ de force, lui accordant +1 à l'Armure (+2 à l'Armure si le niveau du cypher est 5 ou plus). | G39: Certains champs, boucliers et cubes de force sont transparents. D'autres sont translucides. Quelques-uns sont opaques. | I39: 1d6 | J39: (Cypher System Rulebook, page 389) | K39: =TRUE() -> TRUE | L39: =TRUE() -> TRUE | M39: =FALSE() -> FALSE | N39: =LEN(Table1[[#This Row],[effect]]) -> 166 | O39: =Table1[[#This Row],[name]] -> Champ de Force
A40: 2024-10-01T16:53:32.029Z | B40: 2024-10-01T16:53:32.029Z | C40: 2024-10-01T16:53:32.029Z | D40: Vision aux Rayons X | E40: X-Ray Viewer | F40: Permet à l'utilisateur de voir à travers jusqu'à 2 pieds (60 cm) de matériau d'un niveau inférieur à celui du cypher. L'effet dure une minute par niveau de cypher. | I40: 1d6 + 4 | J40: (Cypher System Rulebook, page 400) | K40: =TRUE() -> TRUE | L40: =FALSE() -> FALSE | M40: =FALSE() -> FALSE | N40: =LEN(Table1[[#This Row],[effect]]) -> 167 | O40: =Table1[[#This Row],[name]] -> Vision aux Rayons X
A41: 2024-10-01T16:53:31.807Z | B41: 2024-10-01T16:53:31.807Z | C41: 2024-10-01T16:53:31.807Z | D41: Atténuateur de Son | E41: Sound Dampener | F41: Atténue tout son dans un rayon immédiat pendant une minute par niveau de cypher, offrant un Avantage sur les actions de furtivité pour toutes les créatures de la zone. | I41: 1d6 + 2 | J41: (Cypher System Rulebook, page 397) | K41: =TRUE() -> TRUE | L41: =TRUE() -> TRUE | M41: =FALSE() -> FALSE | N41: =LEN(Table1[[#This Row],[effect]]) -> 167 | O41: =Table1[[#This Row],[name]] -> Atténuateur de Son
A42: 2024-10-01T16:53:31.579Z | B42: 2024-10-01T16:53:31.579Z | C42: 2024-10-01T16:53:31.579Z | D42: Communication Psychique | E42: Psychic Communique | F42: Permet à l'utilisateur de projeter un message télépathique unique et unidirectionnel de jusqu'à dix mots par niveau de cypher, avec une portée illimitée, à quiconque qu'il connaît. | I42: 1d6 + 2 | J42: (Cypher System Rulebook, page 395) | K42: =TRUE() -> TRUE | L42: =TRUE() -> TRUE | M42: =FALSE() -> FALSE | N42: =LEN(Table1[[#This Row],[effect]]) -> 183 | O42: =Table1[[#This Row],[name]] -> Communication Psychique
A43: 2024-10-01T16:53:31.227Z | B43: 2024-10-01T16:53:31.227Z | C43: 2024-10-01T16:53:31.227Z | D43: Projecteur de Bouclier de Force | E43: Force Shield Projector | F43: Crée un bouclier d'énergie scintillant autour de l'utilisateur pendant une heure, durant laquelle il bénéficie de +3 à l'Armure (ou +4 à l'Armure si le cypher est de niveau 5 ou plus). | I43: 1d6 + 3 | J43: (Cypher System Rulebook, page 389) | K43: =TRUE() -> TRUE | L43: =TRUE() -> TRUE | M43: =FALSE() -> FALSE | N43: =LEN(Table1[[#This Row],[effect]]) -> 186 | O43: =Table1[[#This Row],[name]] -> Projecteur de Bouclier de Force
A44: 2024-10-01T16:53:31.281Z | B44: 2024-10-01T16:53:31.281Z | C44: 2024-10-01T16:53:31.281Z | D44: Attaque de Chaleur | E44: Heat Attack | F44: Pendant la journée suivante, chaque fois que l'utilisateur frappe une créature ou un objet solide, l'attaque génère une explosion de chaleur qui inflige 2 points de dégâts supplémentaires. | I44: 1d6 | J44: (Cypher System Rulebook, page 390) | K44: =TRUE() -> TRUE | L44: =TRUE() -> TRUE | M44: =FALSE() -> FALSE | N44: =LEN(Table1[[#This Row],[effect]]) -> 188 | O44: =Table1[[#This Row],[name]] -> Attaque de Chaleur
A45: 2024-10-01T16:53:31.086Z | B45: 2024-10-01T16:53:31.086Z | C45: 2024-10-01T16:53:31.086Z | D45: Détonation (Sonique) | E45: Detonation (Sonic) | F45: Projette un petit explosif physique jusqu'à longue distance qui explose avec un bruit terrifiant, rendant sourds tous ceux dans un rayon immédiat pendant dix minutes par niveau du cypher. | I45: 1d6 + 2 | J45: (Cypher System Rulebook, page 387) | K45: =TRUE() -> TRUE | L45: =FALSE() -> FALSE | M45: =FALSE() -> FALSE | N45: =LEN(Table1[[#This Row],[effect]]) -> 188 | O45: =Table1[[#This Row],[name]] -> Détonation (Sonique)
A46: 2024-10-01T16:53:31.897Z | B46: 2024-10-01T16:53:31.897Z | C46: 2024-10-01T16:53:31.897Z | D46: Téléporteur (Planétaire) | E46: Teleporter (Planetary) | F46: L'utilisateur se téléporte n'importe oà¹ sur la planète vers un endroit qu'il a déjà visité ou vu. Il arrive en toute sécurité avec ses possessions, mais ne peut rien d'autre emporter avec lui. | I46: 1d6 + 4 | J46: (Cypher System Rulebook, page 398) | K46: =TRUE() -> TRUE | L46: =TRUE() -> TRUE | M46: =FALSE() -> FALSE | N46: =LEN(Table1[[#This Row],[effect]]) -> 194 | O46: =Table1[[#This Row],[name]] -> Téléporteur (Planétaire)
A47: 2024-10-01T16:53:31.891Z | B47: 2024-10-01T16:53:31.891Z | C47: 2024-10-01T16:53:31.891Z | D47: Téléporteur (Interstellaire) | E47: Teleporter (Interstellar) | F47: L'utilisateur se téléporte n'importe oà¹ dans la galaxie vers un endroit qu'il a déjà visité ou vu. Il arrive en toute sécurité avec ses possessions, mais ne peut rien d'autre emporter avec lui. | I47: 1d6 + 4 | J47: (Cypher System Rulebook, page 398) | K47: =TRUE() -> TRUE | L47: =TRUE() -> TRUE | M47: =FALSE() -> FALSE | N47: =LEN(Table1[[#This Row],[effect]]) -> 195 | O47: =Table1[[#This Row],[name]] -> Téléporteur (Interstellaire)
A48: 2024-10-01T16:53:31.592Z | B48: 2024-10-01T16:53:31.592Z | C48: 2024-10-01T16:53:31.592Z | D48: Emetteur de Rayon | E48: Ray Emitter | F48: Permet à l'utilisateur de projeter un rayon d'énergie destructrice jusqu'à très longue portée, infligeant des dégâts égaux au niveau du cypher. Lancez un d100 pour déterminer le type d'énergie. | G48: <strong>Emetteurs de Rayon Encore Plus Etranges :</strong> <ul> <li>Retourne la cible à l'envers</li> <li>Inflige des dégâts et rend la chair bleue</li> <li>Rend la cible muette</li> <li>Ne nuit qu'aux plantes</li> <li>Ne nuit qu'à la matière inorganique</li> <li>Transforme la chair en un matériau mort, semblable à de la pierre</li> </ul> | H48: <table class="table table-light table-striped table-sm og-dt"> <thead> <tr> <th scope="col" class="text-center w-15">d100</th> <th>Type d'Energie</th> </tr> </thead> <tbody> <tr> <td scope="col" class="text-center w-15">01&mdash;50</td> <td>Chaleur/lumière concentrée</td> </tr> <tr> <td scope="col" class="text-center w-15">51&mdash;60</td> <td>Radiation perturbatrice cellulaire</td> </tr> <tr> <td scope="col" class="text-center w-15">61&mdash;80</td> <td>Force</td> </tr> <tr> <td scope="col" class="text-center w-15">81&mdash;87</td> <td>Onde magnétique</td> </tr> <tr> <td scope="col" class="text-center w-15">88&mdash;93</td> <td>Perturbation des liaisons moléculaires</td> </tr> <tr> <td scope="col" class="text-center w-15">94&mdash;00</td> <td>Froid concentré</td> </tr> </tbody> </table> | I48: 1d6 + 2 | J48: ((Cypher System Rulebook, page 395) | K48: =TRUE() -> TRUE | L48: =TRUE() -> TRUE | M48: =FALSE() -> FALSE | N48: =LEN(Table1[[#This Row],[effect]]) -> 195 | O48: =Table1[[#This Row],[name]] -> Emetteur de Rayon
A49: 2024-10-01T16:53:31.002Z | B49: 2024-10-01T16:53:31.002Z | C49: 2024-10-01T16:53:31.002Z | D49: Détonation | E49: Detonation | F49: Projette un petit explosif physique jusqu'à longue distance qui explose dans un rayon immédiat, infligeant des dégâts égaux au niveau du cypher. Lancez un d100 pour déterminer le type de dégâts. | G49: Toutes les détonations infligeant des dégâts infligent un minimum de 2 points de dégâts à ceux dans le rayon, quel que soit le jet d'attaque ou de défense. | H49: <table class="table table-light table-striped table-sm og-dt"> <thead> <tr> <th scope="col" class="text-center w-15">d100</th> <th>Type de Détonation</th> </tr> </thead> <tbody> <tr> <td scope="col" class="text-center w-15">01&mdash;10</td> <td>Perturbation cellulaire (n'affecte que la chair)</td> </tr> <tr> <td scope="col" class="text-center w-15">11&mdash;30</td> <td>Corrosif</td> </tr> <tr> <td scope="col" class="text-center w-15">31&mdash;40</td> <td>Décharge électrique</td> </tr> <tr> <td scope="col" class="text-center w-15">41&mdash;50</td> <td>Drain de chaleur (froid)</td> </tr> <tr> <td scope="col" class="text-center w-15">51&mdash;75</td> <td>Feu</td> </tr> <tr> <td scope="col" class="text-center w-15">76&mdash;00</td> <td>Eclats</td> </tr> </tbody> </table> | I49: 1d6 + 2 | J49: (Cypher System Rulebook, page 386) | K49: =TRUE() -> TRUE | L49: =FALSE() -> FALSE | M49: =FALSE() -> FALSE | N49: =LEN(Table1[[#This Row],[effect]]) -> 195 | O49: =Table1[[#This Row],[name]] -> Détonation
A50: 2024-10-01T16:53:31.883Z | B50: 2024-10-01T16:53:31.883Z | C50: 2024-10-01T16:53:31.883Z | D50: Téléporteur (Sauter) | E50: Teleporter (Bounder) | F50: L'utilisateur se téléporte jusqu'à 100 x le niveau du cypher en pieds vers un endroit qu'il peut voir. Il arrive en toute sécurité avec ses possessions, mais ne peut rien d'autre emporter avec lui. | I50: 1d6 + 2 | J50: (Cypher System Rulebook, page 398) | K50: =TRUE() -> TRUE | L50: =TRUE() -> TRUE | M50: =FALSE() -> FALSE | N50: =LEN(Table1[[#This Row],[effect]]) -> 198 | O50: =Table1[[#This Row],[name]] -> Téléporteur (Sauter)
A51: 2024-10-01T16:53:31.607Z | B51: 2024-10-01T16:53:31.607Z | C51: 2024-10-01T16:53:31.607Z | D51: EmetteurEmetteur de Rayon (Peur) de Rayon (Peur) | E51: Ray Emitter (Fear) | F51: Permet à l'utilisateur de projeter un rayon jusqu'à portée longue (très longue portée si le cypher est de niveau 6 ou supérieur) qui provoque la fuite de la cible dans la terreur pendant une minute. | I51: 1d6 + 2 | J51: (Cypher System Rulebook, page 395) | K51: =TRUE() -> TRUE | L51: =TRUE() -> TRUE | M51: =FALSE() -> FALSE | N51: =LEN(Table1[[#This Row],[effect]]) -> 200 | O51: =Table1[[#This Row],[name]] -> EmetteurEmetteur de Rayon (Peur) de Rayon (Peur)
A52: 2024-10-01T16:53:31.057Z | B52: 2024-10-01T16:53:31.057Z | C52: 2024-10-01T16:53:31.057Z | D52: Détonation (Massive) | E52: Detonation (Massive) | F52: Projette un petit explosif physique jusqu'à longue distance qui explose dans un rayon de courte portée, infligeant des dégâts égaux au niveau du cypher. Lancez un d100 pour déterminer le type de dégâts. | H52: <table class="table table-light table-striped table-sm og-dt"> <thead> <tr> <th scope="col" class="text-center w-15">d100</th> <th>Type de Détonation</th> </tr> </thead> <tbody> <tr> <td scope="col" class="text-center w-15">01&mdash;10</td> <td>Perturbation cellulaire (n'affecte que la chair)</td> </tr> <tr> <td scope="col" class="text-center w-15">11&mdash;30</td> <td>Corrosif</td> </tr> <tr> <td scope="col" class="text-center w-15">31&mdash;40</td> <td>Décharge électrique</td> </tr> <tr> <td scope="col" class="text-center w-15">41&mdash;50</td> <td>Drain de chaleur (froid)</td> </tr> <tr> <td scope="col" class="text-center w-15">51&mdash;75</td> <td>Feu</td> </tr> <tr> <td scope="col" class="text-center w-15">76&mdash;00</td> <td>Eclats</td> </tr> </tbody> </table> | I52: 1d6 + 2 | J52: (Cypher System Rulebook, page 387) | K52: =TRUE() -> TRUE | L52: =FALSE() -> FALSE | M52: =FALSE() -> FALSE | N52: =LEN(Table1[[#This Row],[effect]]) -> 203 | O52: =Table1[[#This Row],[name]] -> Détonation (Massive)
A53: 2024-10-01T16:53:31.025Z | B53: 2024-10-01T16:53:31.025Z | C53: 2024-10-01T16:53:31.025Z | D53: Détonation (Flash) | E53: Detonation (Flash) | F53: Projette un petit explosif physique jusqu'à longue distance qui éclate dans un rayon immédiat, aveuglant tous ceux qui s'y trouvent pendant une minute (dix minutes si le cypher est de niveau 4 ou plus). | I53: 1d6 + 2 | J53: (Cypher System Rulebook, page 386) | K53: =TRUE() -> TRUE | L53: =FALSE() -> FALSE | M53: =FALSE() -> FALSE | N53: =LEN(Table1[[#This Row],[effect]]) -> 203 | O53: =Table1[[#This Row],[name]] -> Détonation (Flash)
A54: 2024-10-01T16:53:31.619Z | B54: 2024-10-01T16:53:31.619Z | C54: 2024-10-01T16:53:31.619Z | D54: Emetteur de Rayon (Tuer un Ami) | E54: Ray Emitter (Friend Slaying) | F54: Permet à l'utilisateur de projeter un rayon jusqu'à portée longue (très longue portée si le cypher est de niveau 6 ou supérieur) qui pousse la cible à attaquer son allié le plus proche pendant un round. | I54: 1d6 + 2 | J54: (Cypher System Rulebook, page 395) | K54: =TRUE() -> TRUE | L54: =TRUE() -> TRUE | M54: =FALSE() -> FALSE | N54: =LEN(Table1[[#This Row],[effect]]) -> 205 | O54: =Table1[[#This Row],[name]] -> Emetteur de Rayon (Tuer un Ami)
A55: 2024-10-01T16:53:31.643Z | B55: 2024-10-01T16:53:31.643Z | C55: 2024-10-01T16:53:31.643Z | D55: Emetteur de Rayon (Paralysie) | E55: Ray Emitter (Paralysis) | F55: Permet à l'utilisateur de projeter un rayon d'énergie jusqu'à très longue portée qui paralyse la cible pendant une minute. Un petit nombre de ces dispositifs (5 %) induisent une paralysie qui dure une heure. | I55: 1d6 + 2 | J55: (Cypher System Rulebook, page 395) | K55: =TRUE() -> TRUE | L55: =TRUE() -> TRUE | M55: =FALSE() -> FALSE | N55: =LEN(Table1[[#This Row],[effect]]) -> 209 | O55: =Table1[[#This Row],[name]] -> Emetteur de Rayon (Paralysie)
A56: 2024-10-01T16:53:31.905Z | B56: 2024-10-01T16:53:31.905Z | C56: 2024-10-01T16:53:31.905Z | D56: Téléporteur (Voyageur) | E56: Teleporter (Traveler) | F56: L'utilisateur se téléporte jusqu'à 100 x le niveau du cypher en miles vers un endroit qu'il a déjà visité ou vu. Il arrive en toute sécurité avec ses possessions, mais ne peut rien d'autre emporter avec lui. | I56: 1d6 + 4 | J56: (Cypher System Rulebook, page 398) | K56: =TRUE() -> TRUE | L56: =TRUE() -> TRUE | M56: =FALSE() -> FALSE | N56: =LEN(Table1[[#This Row],[effect]]) -> 209 | O56: =Table1[[#This Row],[name]] -> Téléporteur (Voyageur)
A57: 2024-10-01T16:53:30.974Z | B57: 2024-10-01T16:53:30.974Z | C57: 2024-10-01T16:53:30.974Z | D57: Vision Nocturne | E57: Darksight | F57: Confère la capacité de voir dans le noir pendant cinq heures par niveau du cypher. (Pour un jeu plus réaliste, ce cypher pourrait plutôt rendre l'utilisateur spécialisé dans la détection en faible luminosité.) | I57: 1d6 | J57: (Cypher System Rulebook, page 386) | K57: =TRUE() -> TRUE | L57: =FALSE() -> FALSE | M57: =TRUE() -> TRUE | N57: =LEN(Table1[[#This Row],[effect]]) -> 209 | O57: =Table1[[#This Row],[name]] -> Vision Nocturne
A58: 2024-10-01T16:53:31.063Z | B58: 2024-10-01T16:53:31.063Z | C58: 2024-10-01T16:53:31.063Z | D58: Détonation (Perturbation de la Matière) | E58: Detonation (Matter Disruption) | F58: Projette un petit explosif physique jusqu'à longue distance qui explose dans un rayon immédiat, libérant des nanites qui réarrangent la matière de manière aléatoire. Inflige des dégâts égaux au niveau du cypher. | I58: 1d6 + 4 | J58: (Cypher System Rulebook, page 387) | K58: =TRUE() -> TRUE | L58: =TRUE() -> TRUE | M58: =FALSE() -> FALSE | N58: =LEN(Table1[[#This Row],[effect]]) -> 212 | O58: =Table1[[#This Row],[name]] -> Détonation (Perturbation de la Matière)
A59: 2024-10-01T16:53:30.851Z | B59: 2024-10-01T16:53:30.851Z | C59: 2024-10-01T16:53:30.851Z | D59: Antivenin | E59: Antivenom | F59: Rend l'utilisateur immunisé contre les poisons d'un niveau inférieur ou égal à celui du cypher pendant une heure par niveau du cypher (et annule tout effet en cours déjà présent dans le système de l'utilisateur). | I59: 1d6 + 2 | J59: (Cypher System Rulebook, page 384) | K59: =TRUE() -> TRUE | L59: =FALSE() -> FALSE | M59: =FALSE() -> FALSE | N59: =LEN(Table1[[#This Row],[effect]]) -> 214 | O59: =Table1[[#This Row],[name]] -> Antivenin
A60: 2024-10-01T16:53:31.257Z | B60: 2024-10-01T16:53:31.257Z | C60: 2024-10-01T16:53:31.257Z | D60: Bombe à Gaz | E60: Gas Bomb | F60: Lancée à courte distance, elle explose en un nuage empoisonné couvrant une zone immédiate. Le nuage persiste pendant 1d6 rounds, sauf si les conditions l'indiquent autrement. Lancez un d100 pour déterminer l'effet. | H60: <table class="table table-light table-striped table-sm og-dt"> <thead> <tr> <th scope="col" class="text-center w-15">d100</th> <th>Type de Gaz</th> </tr> </thead> <tbody> <tr> <td scope="col" class="text-center w-15">01&mdash;10</td> <td>Fumée épaisse : occulte la vue tant que le nuage persiste</td> </tr> <tr> <td scope="col" class="text-center w-15">11&mdash;20</td> <td>Gaz d'étouffement : les créatures vivantes qui respirent perdent leurs actions à cause de l'étouffement et de la toux pendant un nombre de rounds égal au niveau du cypher.</td> </tr> <tr> <td scope="col" class="text-center w-15">21&mdash;50</td> <td>Gaz empoisonné : les créatures vivantes qui respirent subissent des dégâts égaux au niveau du cypher.</td> </tr> <tr> <td scope="col" class="text-center w-15">51&mdash;60</td> <td>Gaz corrosif : tout subit des dégâts égaux au niveau du cypher.</td> </tr> <tr> <td scope="col" class="text-center w-15">61&mdash;65</td> <td>Gaz hallucinogène : les créatures vivantes qui respirent perdent leurs actions à cause des hallucinations et visions pendant un nombre de rounds égal au niveau du cypher.</td> </tr> <tr> <td scope="col" class="text-center w-15">66&mdash;70</td> <td>Gaz neurotoxique : les créatures vivantes qui respirent subissent des dégâts en Célérité égaux au niveau du cypher.</td> </tr> <tr> <td scope="col" class="text-center w-15">71&mdash;80</td> <td>Gaz débilitant : les créatures vivantes qui respirent subissent des dégâts en Intellect égaux au niveau du cypher.</td> </tr> <tr> <td scope="col" class="text-center w-15">81&mdash;83</td> <td>Gaz de peur : les créatures vivantes qui respirent et pensent fuient dans une direction aléatoire de peur (ou sont paralysées par la peur) pendant un nombre de rounds égal au niveau du cypher.</td> </tr> <tr> <td scope="col" class="text-center w-15">84&mdash;86</td> <td>Gaz d'amnésie : les créatures vivantes qui respirent et pensent perdent définitivement toute mémoire de la dernière minute.</td> </tr> <tr> <td scope="col" class="text-center w-15">87&mdash;96</td> <td>Gaz soporifique : les créatures vivantes qui respirent s'endorment pendant un nombre de rounds égal au niveau du cypher ou jusqu'à ce qu'elles soient réveillées par une action violente ou un bruit extràêmement fort.</td> </tr> <tr> <td scope="col" class="text-center w-15">97&mdash;00</td> <td>Gaz de rage : les créatures vivantes qui respirent et pensent attaquent au corps à corps la créature la plus proche et continuent à le faire pendant un nombre de rounds égal au niveau du cypher.</td> </tr> </tbody> </table> | I60: 1d6 + 2 | J60: (Cypher System Rulebook, page 389) | K60: =TRUE() -> TRUE | L60: =FALSE() -> FALSE | M60: =FALSE() -> FALSE | N60: =LEN(Table1[[#This Row],[effect]]) -> 215 | O60: =Table1[[#This Row],[name]] -> Bombe à Gaz
A61: 2024-10-01T16:53:31.237Z | B61: 2024-10-01T16:53:31.237Z | C61: 2024-10-01T16:53:31.237Z | D61: Réducteur de Friction | E61: Friction Reducer | F61: Répandu sur une zone allant jusqu'à 3 m carrés (10 pieds carrés), cela rend les choses extràêmement glissantes. Pendant une heure par niveau du cypher, les tâches de mouvement dans la zone sont entravées de trois niveaux. | I61: 1d6 | J61: (Cypher System Rulebook, page 389) | K61: =TRUE() -> TRUE | L61: =FALSE() -> FALSE | M61: =FALSE() -> FALSE | N61: =LEN(Table1[[#This Row],[effect]]) -> 222 | O61: =Table1[[#This Row],[name]] -> Réducteur de Friction
A62: 2024-10-01T16:53:30.936Z | B62: 2024-10-01T16:53:30.936Z | C62: 2024-10-01T16:53:30.936Z | D62: Eliminateur de Conditions | E62: Condition Remover | F62: Guérit une occurrence d'une condition de santé spécifique d'un niveau inférieur ou égal à celui du cypher. Cela n'empàêche pas de futures occurrences de la màême condition. Lancez un d20 pour déterminer ce que cela guérit. | H62: <table class="table table-light table-striped table-sm og-dt"> <thead> <tr> <th>d20</th> <th>Condition</th> </tr> </thead> <tbody> <tr> <td scope="col" class="text-center w-15">1</td> <td>Addiction à une substance</td> </tr> <tr> <td scope="col" class="text-center w-15">2</td> <td>Maladie auto-immune</td> </tr> <tr> <td scope="col" class="text-center w-15">3</td> <td>Infection bactérienne</td> </tr> <tr> <td scope="col" class="text-center w-15">4</td> <td>Mauvaise haleine</td> </tr> <tr> <td scope="col" class="text-center w-15">5</td> <td>Ampoules</td> </tr> <tr> <td scope="col" class="text-center w-15">6</td> <td>Ballonnements</td> </tr> <tr> <td scope="col" class="text-center w-15">7</td> <td>Cancer</td> </tr> <tr> <td scope="col" class="text-center w-15">8</td> <td>Lèvres gercées</td> </tr> <tr> <td scope="col" class="text-center w-15">9</td> <td>Flatulence</td> </tr> <tr> <td scope="col" class="text-center w-15">10</td> <td>Gueule de bois</td> </tr> <tr> <td scope="col" class="text-center w-15">11</td> <td>Brà»lures d'estomac</td> </tr> <tr> <td scope="col" class="text-center w-15">12</td> <td>Hoquet</td> </tr> <tr> <td scope="col" class="text-center w-15">13</td> <td>Poils incarnés</td> </tr> <tr> <td scope="col" class="text-center w-15">14</td> <td>Insomnie</td> </tr> <tr> <td scope="col" class="text-center w-15">15</td> <td>Problème articulaire</td> </tr> <tr> <td scope="col" class="text-center w-15">16</td> <td>Crampes musculaires</td> </tr> <tr> <td scope="col" class="text-center w-15">17</td> <td>Boutons</td> </tr> <tr> <td scope="col" class="text-center w-15">18</td> <td>Psychose</td> </tr> <tr> <td scope="col" class="text-center w-15">19</td> <td>Torticolis</td> </tr> <tr> <td scope="col" class="text-center w-15">20</td> <td>Infection virale</td> </tr> </tbody> </table> | I62: 1d6 + 3 | J62: (Cypher System Rulebook, page 385) | K62: =FALSE() -> FALSE | L62: =TRUE() -> TRUE | M62: =FALSE() -> FALSE | N62: =LEN(Table1[[#This Row],[effect]]) -> 223 | O62: =Table1[[#This Row],[name]] -> Eliminateur de Conditions
A63: 2024-10-01T16:53:30.922Z | B63: 2024-10-01T16:53:30.922Z | C63: 2024-10-01T16:53:30.922Z | D63: Usine Chimique | E63: Chemical Factory | F63: Après une heure, la sueur de l'utilisateur produit 1d6 doses d'un liquide précieux (ces doses ne sont pas considérées comme des cyphers). Elles doivent àêtre utilisées dans la semaine. Lancez un d100 pour déterminer l'effet. | H63: <table class="table table-light table-striped table-sm og-dt"> <thead> <tr> <th scope="col" class="text-center w-15">d100</th> <th>Effet du liquide</th> </tr> </thead> <tbody> <tr> <td scope="col" class="text-center w-15">01&mdash;04</td> <td>Euphorique pendant 1d6 heures</td> </tr> <tr> <td scope="col" class="text-center w-15">05&mdash;08</td> <td>Hallucinogène pendant 1d6 heures</td> </tr> <tr> <td scope="col" class="text-center w-15">09&mdash;12</td> <td>Stimulant pendant 1d6 heures</td> </tr> <tr> <td scope="col" class="text-center w-15">13&mdash;16</td> <td>Dépresseur pendant 1d6 heures</td> </tr> <tr> <td scope="col" class="text-center w-15">17&mdash;20</td> <td>Supplément nutritionnel</td> </tr> <tr> <td scope="col" class="text-center w-15">21&mdash;25</td> <td>Antivenin</td> </tr> <tr> <td scope="col" class="text-center w-15">26&mdash;30</td> <td>Guérit une maladie</td> </tr> <tr> <td scope="col" class="text-center w-15">31&mdash;35</td> <td>Voir dans le noir pendant une heure</td> </tr> <tr> <td scope="col" class="text-center w-15">36&mdash;45</td> <td>Restaure un nombre de points de la Réserve de Puissance égal au niveau du cypher</td> </tr> <tr> <td scope="col" class="text-center w-15">46&mdash;55</td> <td>Restaure un nombre de points de la Réserve de Célérité égal au niveau du cypher</td> </tr> <tr> <td scope="col" class="text-center w-15">56&mdash;65</td> <td>Restaure un nombre de points de la Réserve d'Intellect égal au niveau du cypher</td> </tr> <tr> <td scope="col" class="text-center w-15">66&mdash;75</td> <td>Augmente l'Avantage de Puissance de 1 pendant une heure</td> </tr> <tr> <td scope="col" class="text-center w-15">76&mdash;85</td> <td>Augmente l'Avantage de Célérité de 1 pendant une heure</td> </tr> <tr> <td scope="col" class="text-center w-15">86&mdash;95</td> <td>Augmente l'Avantage d'Intellect de 1 pendant une heure</td> </tr> <tr> <td scope="col" class="text-center w-15">96&mdash;00</td> <td>Restaure toutes les Réserves au maximum</td> </tr> </tbody> </table> | I63: 1d6 | J63: (Cypher System Rulebook, page 385) | K63: =TRUE() -> TRUE | L63: =TRUE() -> TRUE | M63: =FALSE() -> FALSE | N63: =LEN(Table1[[#This Row],[effect]]) -> 224 | O63: =Table1[[#This Row],[name]] -> Usine Chimique
A64: 2024-10-01T16:53:31.506Z | B64: 2024-10-01T16:53:31.506Z | C64: 2024-10-01T16:53:31.506Z | D64: Champ Nul | E64: Null Field | F64: L'utilisateur et toutes les créatures dans la portée immédiate gagnent +3 à l'Armure (+5 si le cypher est de niveau 8 ou supérieur) contre des dégâts d'un type spécifié pendant une heure. Lancez un d100 pour déterminer l'effet. | H64: <table class="table table-light table-striped table-sm og-dt"> <thead> <tr> <th scope="col" class="text-center w-15">d100</th> <th>Effect</th> </tr> </thead> <tbody> <tr> <td scope="col" class="text-center w-15">01&mdash;12</td> <td>Feu</td> </tr> <tr> <td scope="col" class="text-center w-15">13&mdash;27</td> <td>Froid</td> </tr> <tr> <td scope="col" class="text-center w-15">28&mdash;39</td> <td>Acide</td> </tr> <tr> <td scope="col" class="text-center w-15">40&mdash;52</td> <td>Psychique</td> </tr> <tr> <td scope="col" class="text-center w-15">53&mdash;65</td> <td>Sonique</td> </tr> <tr> <td scope="col" class="text-center w-15">66&mdash;72</td> <td>Electrique</td> </tr> <tr> <td scope="col" class="text-center w-15">73&mdash;84</td> <td>Poison</td> </tr> <tr> <td scope="col" class="text-center w-15">85&mdash;95</td> <td>Force contondante</td> </tr> <tr> <td scope="col" class="text-center w-15">96&mdash;00</td> <td>Tranchant et perà§ant</td> </tr> </tbody> </table> | I64: 1d6 + 3 | J64: (Cypher System Rulebook, page 393) | K64: =TRUE() -> TRUE | L64: =TRUE() -> TRUE | M64: =FALSE() -> FALSE | N64: =LEN(Table1[[#This Row],[effect]]) -> 228 | O64: =Table1[[#This Row],[name]] -> Champ Nul
A65: 2024-10-01T16:53:31.402Z | B65: 2024-10-01T16:53:31.402Z | C65: 2024-10-01T16:53:31.402Z | D65: Bouclier Magnétique | E65: Magnetic Shield | F65: Pendant dix minutes par niveau de cypher, les objets métalliques ne peuvent pas se trouver à portée immédiate de l'utilisateur. Les objets métalliques déjà dans la zone lorsque le dispositif est activé sont lentement repoussés. | I65: 1d6 + 2 | J65: (Cypher System Rulebook, page 392) | K65: =TRUE() -> TRUE | L65: =TRUE() -> TRUE | M65: =FALSE() -> FALSE | N65: =LEN(Table1[[#This Row],[effect]]) -> 229 | O65: =Table1[[#This Row],[name]] -> Bouclier Magnétique
A66: 2024-10-01T16:53:31.197Z | B66: 2024-10-01T16:53:31.197Z | C66: 2024-10-01T16:53:31.197Z | D66: Mur Ignifuge | E66: Flame-Retardant Wall | F66: Crée un plan immobile d'énergie perméable mesurant jusqu'à 6 m par 6 m (20 pieds par 20 pieds) pendant une heure par niveau du cypher. Le plan se conforme à l'espace disponible. Les flammes passant à travers le plan sont éteintes. | I66: 1d6 | J66: (Cypher System Rulebook, page 388) | K66: =TRUE() -> TRUE | L66: =TRUE() -> TRUE | M66: =FALSE() -> FALSE | N66: =LEN(Table1[[#This Row],[effect]]) -> 233 | O66: =Table1[[#This Row],[name]] -> Mur Ignifuge
A67: 2024-10-01T16:53:30.992Z | B67: 2024-10-01T16:53:30.992Z | C67: 2024-10-01T16:53:30.992Z | D67: Densité | E67: Density | F67: Pendant la journée suivante, chaque fois que l'utilisateur frappe une créature ou un objet solide avec une arme, l'arme voit soudainement son poids augmenter de manière spectaculaire, ce qui inflige 2 points de dégâts supplémentaires. | I67: 1d6 | J67: (Cypher System Rulebook, page 386) | K67: =TRUE() -> TRUE | L67: =FALSE() -> FALSE | M67: =FALSE() -> FALSE | N67: =LEN(Table1[[#This Row],[effect]]) -> 234 | O67: =Table1[[#This Row],[name]] -> Densité
A68: 2024-10-01T16:53:31.978Z | B68: 2024-10-01T16:53:31.978Z | C68: 2024-10-01T16:53:31.978Z | D68: Dispositif de Déplacement Visuel | E68: Visual Displacement Device | F68: Projette des images holographiques de l'utilisateur pour tromper les attaquants. Les images apparaissent autour de l'utilisateur, lui offrant un Avantage pour les actions de Défense de Célérité pendant dix minutes par niveau de cypher. | I68: 1d6 | J68: (Cypher System Rulebook, page 399) | K68: =TRUE() -> TRUE | L68: =TRUE() -> TRUE | M68: =FALSE() -> FALSE | N68: =LEN(Table1[[#This Row],[effect]]) -> 235 | O68: =Table1[[#This Row],[name]] -> Dispositif de Déplacement Visuel
A69: 2024-10-01T16:53:31.469Z | B69: 2024-10-01T16:53:31.469Z | C69: 2024-10-01T16:53:31.469Z | D69: Fusion Mentale | E69: Mind Meld | F69: Permet à l'utilisateur de parler télépathiquement avec des créatures qu'il peut voir à portée courte pendant jusqu'à une heure. L'utilisateur ne peut pas lire les pensées d'une cible, sauf celles qui sont spécifiquement "transmises". | I69: 1d6 + 1 | J69: (Cypher System Rulebook, page 393) | K69: =TRUE() -> TRUE | L69: =TRUE() -> TRUE | M69: =FALSE() -> FALSE | N69: =LEN(Table1[[#This Row],[effect]]) -> 236 | O69: =Table1[[#This Row],[name]] -> Fusion Mentale
A70: 2024-10-01T16:53:32.038Z | B70: 2024-10-01T16:53:32.038Z | C70: 2024-10-01T16:53:32.038Z | D70: Champ de Point Zéro | E70: Zero Point Field | F70: Rend un objet inanimé à l'extérieur des effets de la plupart des énergies pendant une minute. Cela signifie que l'objet ne peut pas àêtre endommagé, déplacé ou manipulé de quelque manière que ce soit. Il reste en place (màême en l'air). | I70: 1d6 + 3 | J70: (Cypher System Rulebook, page 400) | K70: =TRUE() -> TRUE | L70: =TRUE() -> TRUE | M70: =FALSE() -> FALSE | N70: =LEN(Table1[[#This Row],[effect]]) -> 237 | O70: =Table1[[#This Row],[name]] -> Champ de Point Zéro
A71: 2024-10-01T16:53:31.994Z | B71: 2024-10-01T16:53:31.994Z | C71: 2024-10-01T16:53:31.994Z | D71: Chaleur | E71: Warmth | F71: Garde l'utilisateur au chaud et à l'aise, màême dans les températures les plus froides, pendant vingt-quatre heures. Pendant ce temps, l'utilisateur bénéficie d'une Armure égale au niveau du cypher qui protège contre les dégâts de froid. | I71: 1d6 | J71: (Cypher System Rulebook, page 400) | K71: =TRUE() -> TRUE | L71: =FALSE() -> FALSE | M71: =FALSE() -> FALSE | N71: =LEN(Table1[[#This Row],[effect]]) -> 238 | O71: =Table1[[#This Row],[name]] -> Chaleur
A72: 2024-10-01T16:53:30.966Z | B72: 2024-10-01T16:53:30.966Z | C72: 2024-10-01T16:53:30.966Z | D72: Porteur de Malédiction | E72: Curse Bringer | F72: Le cypher peut àêtre activé lorsqu'il est donné à une personne qui n'en connaît pas l'importance. La prochaine fois que la victime tente une tâche importante alors qu'elle est en possession du cypher, la tâche est entravée de trois crans. | I72: 1d6 + 1 | J72: (Cypher System Rulebook, page 386) | K72: =TRUE() -> TRUE | L72: =FALSE() -> FALSE | M72: =FALSE() -> FALSE | N72: =LEN(Table1[[#This Row],[effect]]) -> 239 | O72: =Table1[[#This Row],[name]] -> Porteur de Malédiction
A73: 2024-10-01T16:53:31.667Z | B73: 2024-10-01T16:53:31.667Z | C73: 2024-10-01T16:53:31.667Z | D73: Amplificateur de Réflexes | E73: Reflex Enhancer | F73: Toutes les tâches impliquant de la dextérité manuelle - telles que le vol à la tire, le crochetage, le jonglage, les opérations chirurgicales sur un patient, le désamorà§age d'une bombe, etc. - sont facilitées de deux niveaux pendant une heure. | I73: 1d6 | J73: (Cypher System Rulebook, page 395) | K73: =FALSE() -> FALSE | L73: =FALSE() -> FALSE | M73: =TRUE() -> TRUE | N73: =LEN(Table1[[#This Row],[effect]]) -> 245 | O73: =Table1[[#This Row],[name]] -> Amplificateur de Réflexes
A74: 2024-10-01T16:53:31.386Z | B74: 2024-10-01T16:53:31.386Z | C74: 2024-10-01T16:53:31.386Z | D74: Foreuse d'Attaque Magnétique | E74: Magnetic Attack Drill | F74: L'utilisateur lance ce cypher sur une cible à portée courte, et il s'enfonce dans la cible pendant un tour, infligeant des dégâts égaux au niveau du cypher. Si la cible est en métal ou porte du métal (comme une armure), l'attaque est facilitée. | I74: 1d6 + 2 | J74: (Cypher System Rulebook, page 392) | K74: =TRUE() -> TRUE | L74: =TRUE() -> TRUE | M74: =FALSE() -> FALSE | N74: =LEN(Table1[[#This Row],[effect]]) -> 245 | O74: =Table1[[#This Row],[name]] -> Foreuse d'Attaque Magnétique
A75: 2024-10-01T16:53:31.247Z | B75: 2024-10-01T16:53:31.247Z | C75: 2024-10-01T16:53:31.247Z | D75: Mur Frigorifique | E75: Frigid Wall | F75: Crée un mur d'air super-refroidi mesurant jusqu'à 9 m par 9 m par 30 cm (30 pieds par 30 pieds par 1 pied) qui inflige des dégâts égaux au niveau du cypher à tout ce qui le traverse. Le mur se conforme à l'espace disponible et dure dix minutes. | I75: 1d6 + 2 | J75: (Cypher System Rulebook, page 389) | K75: =TRUE() -> TRUE | L75: =TRUE() -> TRUE | M75: =FALSE() -> FALSE | N75: =LEN(Table1[[#This Row],[effect]]) -> 247 | O75: =Table1[[#This Row],[name]] -> Mur Frigorifique
A76: 2024-10-01T16:53:31.307Z | B76: 2024-10-01T16:53:31.307Z | C76: 2024-10-01T16:53:31.307Z | D76: Mur Infernal | E76: Inferno Wall | F76: Crée un mur de chaleur extràême mesurant jusqu'à 30 pieds par 30 pieds par 1 pied (9 m par 9 m par 30 cm) qui inflige des dégâts égaux au niveau du cypher à tout ce qui passe à travers. Le mur s'adapte à l'espace disponible. Il dure dix minutes. | I76: 1d6 + 2 | J76: (Cypher System Rulebook, page 390) | K76: =TRUE() -> TRUE | L76: =TRUE() -> TRUE | M76: =FALSE() -> FALSE | N76: =LEN(Table1[[#This Row],[effect]]) -> 249 | O76: =Table1[[#This Row],[name]] -> Mur Infernal
A77: 2024-10-01T16:53:31.135Z | B77: 2024-10-01T16:53:31.135Z | C77: 2024-10-01T16:53:31.135Z | D77: Oeil d'Aigle | E77: Eagleseye | F77: Donne la capacité de voir dix fois plus loin que la normale pendant une heure par niveau du cypher. (Pour un jeu plus réaliste, le cypher Å“il d'aigle pourrait à la place accorder deux atouts pour les tâches impliquant la vision à longue distance.) | I77: 1d6 | J77: (Cypher System Rulebook, page 388) | K77: =FALSE() -> FALSE | L77: =FALSE() -> FALSE | M77: =TRUE() -> TRUE | N77: =LEN(Table1[[#This Row],[effect]]) -> 250 | O77: =Table1[[#This Row],[name]] -> Oeil d'Aigle
A78: 2024-10-01T16:53:31.459Z | B78: 2024-10-01T16:53:31.459Z | C78: 2024-10-01T16:53:31.459Z | D78: Mort Métallique | E78: Metal Death | F78: Produit un flux de mousse qui couvre une zone d'environ 3 pieds par 3 pieds (1 m par 1 m), transformant tout métal qu'elle touche en une substance aussi fragile que du verre fin. La mousse affecte le métal sur une profondeur d'environ 6 pouces (15 cm). | I78: 1d6 + 2 | J78: (Cypher System Rulebook, page 393) | K78: =TRUE() -> TRUE | L78: =FALSE() -> FALSE | M78: =FALSE() -> FALSE | N78: =LEN(Table1[[#This Row],[effect]]) -> 252 | O78: =Table1[[#This Row],[name]] -> Mort Métallique
A79: 2024-10-01T16:53:31.913Z | B79: 2024-10-01T16:53:31.913Z | C79: 2024-10-01T16:53:31.913Z | D79: Vision Temporelle | E79: Temporal Viewer | F79: Affiche des images et des sons animés, jusqu'à dix minutes par niveau de cypher, représentant des événements qui se sont produits à l'emplacement actuel jusqu'à un an auparavant. L'utilisateur spécifie la période de temps montrée par le visualiseur. | I79: 1d6 + 4 | J79: (Cypher System Rulebook, page 399) | K79: =TRUE() -> TRUE | L79: =TRUE() -> TRUE | M79: =FALSE() -> FALSE | N79: =LEN(Table1[[#This Row],[effect]]) -> 252 | O79: =Table1[[#This Row],[name]] -> Vision Temporelle
A80: 2024-10-01T16:53:31.928Z | B80: 2024-10-01T16:53:31.928Z | C80: 2024-10-01T16:53:31.928Z | D80: Dilatation Temporelle (Offensive) | E80: Time Dilation (Offensive) | F80: Pendant les vingt-quatre heures suivantes, lorsque l'utilisateur effectue une attaque au corps à corps, il se déplace à une vitesse presque instantanée, facilitant ses attaques de deux niveaux (trois niveaux si le cypher est de niveau 6 ou supérieur). | I80: 1d6 | J80: (Cypher System Rulebook, page 399) | K80: =TRUE() -> TRUE | L80: =TRUE() -> TRUE | M80: =FALSE() -> FALSE | N80: =LEN(Table1[[#This Row],[effect]]) -> 253 | O80: =Table1[[#This Row],[name]] -> Dilatation Temporelle (Offensive)
A81: 2024-10-01T16:53:30.867Z | B81: 2024-10-01T16:53:30.867Z | C81: 2024-10-01T16:53:30.867Z | D81: Attracteur | E81: Attractor | F81: Un objet non ancré de la taille de l'utilisateur ou plus petit, situé à longue portée (très longue portée si le niveau du cypher est de 8 ou plus), est immédiatement attiré vers l'utilisateur. Cela prend un tour. L'objet n'a aucun élan lorsqu'il arrive. | I81: 1d6 + 4 | J81: (Cypher System Rulebook, page 384) | K81: =TRUE() -> TRUE | L81: =FALSE() -> FALSE | M81: =FALSE() -> FALSE | N81: =LEN(Table1[[#This Row],[effect]]) -> 254 | O81: =Table1[[#This Row],[name]] -> Attracteur
A82: 2024-10-01T16:53:31.369Z | B82: 2024-10-01T16:53:31.369Z | C82: 2024-10-01T16:53:31.369Z | D82: Mur d'Eclairs | E82: Lightning Wall | F82: Crée un mur de décharges électriques mesurant jusqu'à 30 pieds par 30 pieds par 1 pied (9 m par 9 m par 30 cm) qui inflige des dégâts égaux au niveau du cypher à tout ce qui passe à travers. Le mur s'adapte à l'espace disponible. Il dure dix minutes. | I82: 1d6 + 2 | J82: (Cypher System Rulebook, page 391) | K82: =TRUE() -> TRUE | L82: =TRUE() -> TRUE | M82: =FALSE() -> FALSE | N82: =LEN(Table1[[#This Row],[effect]]) -> 254 | O82: =Table1[[#This Row],[name]] -> Mur d'Eclairs
A83: 2024-10-01T16:53:31.016Z | B83: 2024-10-01T16:53:31.016Z | C83: 2024-10-01T16:53:31.016Z | D83: Détonation (Desséchant) | E83: Detonation (Desiccating) | F83: Projette un petit explosif physique jusqu'à longue distance qui éclate dans un rayon immédiat, drainant l'humidité de tout ce qui s'y trouve. Les créatures vivantes subissent des dégâts égaux au niveau du cypher. L'eau présente dans la zone est vaporisée. | I83: 1d6 + 2 | J83: (Cypher System Rulebook, page 386) | K83: =TRUE() -> TRUE | L83: =TRUE() -> TRUE | M83: =FALSE() -> FALSE | N83: =LEN(Table1[[#This Row],[effect]]) -> 256 | O83: =Table1[[#This Row],[name]] -> Détonation (Desséchant)
A84: 2024-10-01T16:53:31.176Z | B84: 2024-10-01T16:53:31.176Z | C84: 2024-10-01T16:53:31.176Z | D84: Cache d'Equipement | E84: Equipment Cache | F84: L'utilisateur peut fouiller dans le cypher et produire un équipement désiré (pas un artefact) dont le niveau ne dépasse pas celui du cypher. L'équipement persiste jusqu'à une journée, sauf si sa nature fondamentale permet un usage unique (comme une grenade). | I84: 1d6 + 1 | J84: (Cypher System Rulebook, page 388) | K84: =TRUE() -> TRUE | L84: =FALSE() -> FALSE | M84: =FALSE() -> FALSE | N84: =LEN(Table1[[#This Row],[effect]]) -> 259 | O84: =Table1[[#This Row],[name]] -> Cache d'Equipement
A85: 2024-10-01T16:53:31.707Z | B85: 2024-10-01T16:53:31.707Z | C85: 2024-10-01T16:53:31.707Z | D85: Répéteur | E85: Repeater | F85: Pendant la minute suivante, l'arme à distance de l'utilisateur tire une fois de plus avec des munitions fabriquées par le cypher. Le porteur de l'arme peut viser le tir supplémentaire sur la màême cible ou sur une cible différente à proximité de la première. | I85: 1d6 + 1 | J85: (Cypher System Rulebook, page 396) | K85: =TRUE() -> TRUE | L85: =TRUE() -> TRUE | M85: =FALSE() -> FALSE | N85: =LEN(Table1[[#This Row],[effect]]) -> 260 | O85: =Table1[[#This Row],[name]] -> Répéteur
A86: 2024-10-01T16:53:31.861Z | B86: 2024-10-01T16:53:31.861Z | C86: 2024-10-01T16:53:31.861Z | D86: Amplificateur de Puissance | E86: Strength Enhancer | F86: Toutes les tâches non-combattantes impliquant de la force brute&mdash;comme forcer une porte, soulever un lourd rocher, ouvrir des portes d'ascenseur, participer à une compétition de haltérophilie, etc.&mdash;sont facilitées de deux niveaux pendant une heure. | I86: 1d6 | J86: (Cypher System Rulebook, page 398) | K86: =FALSE() -> FALSE | L86: =FALSE() -> FALSE | M86: =TRUE() -> TRUE | N86: =LEN(Table1[[#This Row],[effect]]) -> 260 | O86: =Table1[[#This Row],[name]] -> Amplificateur de Puissance
A87: 2024-10-01T16:53:31.598Z | B87: 2024-10-01T16:53:31.598Z | C87: 2024-10-01T16:53:31.598Z | D87: Emetteur de Rayon (Commande) | E87: Ray Emitter (Command) | F87: Permet à l'utilisateur de projeter un rayon jusqu'à portée longue (très longue portée si le cypher est de niveau 6 ou supérieur) qui force une cible à obéir à la prochaine commande verbale donnée (si elle est comprise) pendant un round par niveau de cypher. | I87: 1d6 + 2 | J87: (Cypher System Rulebook, page 395) | K87: =TRUE() -> TRUE | L87: =TRUE() -> TRUE | M87: =FALSE() -> FALSE | N87: =LEN(Table1[[#This Row],[effect]]) -> 261 | O87: =Table1[[#This Row],[name]] -> Emetteur de Rayon (Commande)
A88: 2024-10-01T16:53:31.970Z | B88: 2024-10-01T16:53:31.970Z | C88: 2024-10-01T16:53:31.970Z | D88: Changeur de Visage | E88: Visage Changer | F88: Change l'apparence d'une créature de taille humaine, fournissant un Avantage pour les tâches de déguisement (facilitant ces tâches de deux niveaux si le cypher est de niveau 5 ou supérieur). Le changement prend dix minutes à appliquer et dure vingt-quatre heures. | I88: 1d6 | J88: (Cypher System Rulebook, page 399) | K88: =TRUE() -> TRUE | L88: =TRUE() -> TRUE | M88: =FALSE() -> FALSE | N88: =LEN(Table1[[#This Row],[effect]]) -> 264 | O88: =Table1[[#This Row],[name]] -> Changeur de Visage
A89: 2024-10-01T16:53:31.490Z | B89: 2024-10-01T16:53:31.490Z | C89: 2024-10-01T16:53:31.490Z | D89: Monolame | E89: Monoblade | F89: Produit une lame de 6 pouces (15 cm) qui est du màême niveau que le cypher. La lame coupe à travers tout matériau de niveau inférieur au sien. Si utilisée comme arme, c'est une arme légère qui ignore l'Armure d'un niveau inférieur au sien. La lame dure dix minutes. | I89: 1d6 + 2 | J89: (Cypher System Rulebook, page 393) | K89: =TRUE() -> TRUE | L89: =TRUE() -> TRUE | M89: =FALSE() -> FALSE | N89: =LEN(Table1[[#This Row],[effect]]) -> 266 | O89: =Table1[[#This Row],[name]] -> Monolame
A90: 2024-10-01T16:53:31.556Z | B90: 2024-10-01T16:53:31.556Z | C90: 2024-10-01T16:53:31.556Z | D90: Poison (Explosif) | E90: Poison (Explosive) | F90: Une fois que cette substance pénètre dans la circulation sanguine, elle se dirige vers le cerveau et se réorganise en un explosif qui explose lorsqu'il est activé, infligeant 10 points de dégâts (ignore l'Armure). Lancez un d100 pour déterminer ce qui active le poison. | H90: <table class="table table-light table-striped table-sm og-dt"> <thead> <tr> <th scope="col" class="text-center w-15">d100</th> <th>Activation</th> </tr> </thead> <tbody> <tr> <td scope="col" class="text-center w-15">01&mdash;25</td> <td>Le détonateur est activé (doit àêtre à portée longue).</td> </tr> <tr> <td scope="col" class="text-center w-15">26&mdash;40</td> <td>Un délai spécifié s'écoule.</td> </tr> <tr> <td scope="col" class="text-center w-15">41&mdash;50</td> <td>La victime effectue une action spécifique.</td> </tr> <tr> <td scope="col" class="text-center w-15">51&mdash;55</td> <td>Une note spécifique est chantée ou jouée sur un instrument à portée courte.</td> </tr> <tr> <td scope="col" class="text-center w-15">56&mdash;60</td> <td>La victime sent une odeur spécifique dans la portée immédiate.</td> </tr> <tr> <td scope="col" class="text-center w-15">61&mdash;80</td> <td>La victime se rapproche à portée longue du détonateur.</td> </tr> <tr> <td scope="col" class="text-center w-15">81&mdash;00</td> <td>La victime n'est plus à portée longue du détonateur.</td> </tr> </tbody> </table> | I90: 1d6 + 1 | J90: (Cypher System Rulebook, page 394) | K90: =TRUE() -> TRUE | L90: =TRUE() -> TRUE | M90: =FALSE() -> FALSE | N90: =LEN(Table1[[#This Row],[effect]]) -> 269 | O90: =Table1[[#This Row],[name]] -> Poison (Explosif)
A91: 2024-10-01T16:53:31.071Z | B91: 2024-10-01T16:53:31.071Z | C91: 2024-10-01T16:53:31.071Z | D91: Détonation (Pression) | E91: Detonation (Pressure) | F91: Projette un petit explosif physique jusqu'à longue distance qui explose dans un rayon immédiat, infligeant des dégâts d'impact égaux au niveau du cypher. Déplace également les objets non surveillés hors de la zone s'ils pèsent moins de 20 livres (9 kg) par niveau du cypher. | I91: 1d6 + 2 | J91: (Cypher System Rulebook, page 387) | K91: =TRUE() -> TRUE | L91: =FALSE() -> FALSE | M91: =FALSE() -> FALSE | N91: =LEN(Table1[[#This Row],[effect]]) -> 275 | O91: =Table1[[#This Row],[name]] -> Détonation (Pression)
A92: 2024-10-01T16:53:31.264Z | B92: 2024-10-01T16:53:31.264Z | C92: 2024-10-01T16:53:31.264Z | D92: Nullificateur de Gravité | E92: Gravity Nullifier | F92: Pendant une heure, l'utilisateur peut flotter dans les airs, se déplaà§ant verticalement d'une courte distance par round (mais pas horizontalement sans une autre action, comme se pousser contre un plafond). L'utilisateur doit peser moins de 23 kg (50 livres) par niveau du cypher. | I92: 1d6 + 3 | J92: (Cypher System Rulebook, page 390) | K92: =TRUE() -> TRUE | L92: =TRUE() -> TRUE | M92: =FALSE() -> FALSE | N92: =LEN(Table1[[#This Row],[effect]]) -> 280 | O92: =Table1[[#This Row],[name]] -> Nullificateur de Gravité
A93: 2024-10-01T16:53:31.440Z | B93: 2024-10-01T16:53:31.440Z | C93: 2024-10-01T16:53:31.440Z | D93: Interrupteur de Mémoire | E93: Memory Switch | F93: L'utilisateur sélectionne un point à portée longue, et les esprits de toutes les créatures pensantes dans la portée immédiate de ce point sont attaqués. Les victimes sont étourdies et ne prennent aucune action pendant un tour, et elles n'ont aucun souvenir de l'heure précédente. | I93: 1d6 + 2 | J93: (Cypher System Rulebook, page 392) | K93: =TRUE() -> TRUE | L93: =TRUE() -> TRUE | M93: =FALSE() -> FALSE | N93: =LEN(Table1[[#This Row],[effect]]) -> 280 | O93: =Table1[[#This Row],[name]] -> Interrupteur de Mémoire
A94: 2024-10-01T16:53:31.835Z | B94: 2024-10-01T16:53:31.835Z | C94: 2024-10-01T16:53:31.835Z | D94: Gardien de Stase | E94: Stasis Keeper | F94: Met un sujet en stase pendant un nombre de jours égal au niveau du cypher, ou jusqu'à ce qu'il soit violemment perturbé. Un objet en stase ne vieillit pas et sort de la stase vivant et dans le màême état que celui dans lequel il est entré, sans mémoire de la période d'inactivité. | I94: 1d6 | J94: (Cypher System Rulebook, page 398) | K94: =TRUE() -> TRUE | L94: =TRUE() -> TRUE | M94: =FALSE() -> FALSE | N94: =LEN(Table1[[#This Row],[effect]]) -> 281 | O94: =Table1[[#This Row],[name]] -> Gardien de Stase
A95: 2024-10-01T16:53:30.840Z | B95: 2024-10-01T16:53:30.840Z | C95: 2024-10-01T16:53:30.840Z | D95: Preneur d'à‚ge | E95: Age Taker | F95: Commence un processus de rajeunissement qui enlève des années à l'âge physiologique du porteur. Au cours des sept prochains jours, le porteur perd un nombre d'années égal à trois fois le niveau du cypher. Le cypher ne ramène pas l'âge physiologique en dessous de vingt-trois ans. | I95: 1d6 + 4 | J95: (Cypher System Rulebook, page 384) | K95: =TRUE() -> TRUE | L95: =TRUE() -> TRUE | M95: =FALSE() -> FALSE | N95: =LEN(Table1[[#This Row],[effect]]) -> 281 | O95: =Table1[[#This Row],[name]] -> Preneur d'à‚ge
A96: 2024-10-01T16:53:31.683Z | B96: 2024-10-01T16:53:31.683Z | C96: 2024-10-01T16:53:31.683Z | D96: Souvenir | E96: Remembering | F96: Permet à l'utilisateur de se souvenir de n'importe quelle expérience qu'il a déjà vécue. L'expérience ne peut pas durer plus d'une minute par niveau de cypher, mais le rappel est parfait, donc (par exemple) s'il a vu quelqu'un composer un numéro de téléphone, il se souviendra du numéro. | I96: 1d6 | J96: (Cypher System Rulebook, page 396) | K96: =FALSE() -> FALSE | L96: =FALSE() -> FALSE | M96: =TRUE() -> TRUE | N96: =LEN(Table1[[#This Row],[effect]]) -> 289 | O96: =Table1[[#This Row],[name]] -> Souvenir
A97: 2024-10-01T16:53:31.183Z | B97: 2024-10-01T16:53:31.183Z | C97: 2024-10-01T16:53:31.183Z | D97: Vision à Distance | E97: Farsight | F97: L'utilisateur peut observer un endroit qu'il a déjà visité, peu importe la distance (màême à travers des galaxies). Cette vision persiste pendant dix minutes par niveau du cypher. Le personnage peut alterner entre la vision de cet endroit et celle de son emplacement actuel une fois par round. | I97: 1d6 + 1 | J97: (Cypher System Rulebook, page 388) | K97: =TRUE() -> TRUE | L97: =TRUE() -> TRUE | M97: =FALSE() -> FALSE | N97: =LEN(Table1[[#This Row],[effect]]) -> 295 | O97: =Table1[[#This Row],[name]] -> Vision à Distance
A98: 2024-10-01T16:53:31.274Z | B98: 2024-10-01T16:53:31.274Z | C98: 2024-10-01T16:53:31.274Z | D98: Application Nullifiant la Gravité | E98: Gravity-Nullifying Application | F98: Si un objet non vivant ne dépassant pas la taille d'un humain (deux humains si le niveau du cypher est 6 ou plus) est recouvert par ce cypher, il flotte à une hauteur de 1d20 pieds dans les airs de manière permanente et n'a plus de poids s'il est porté (bien qu'il doive àêtre solidement attaché). | I98: 1d6 + 2 | J98: (Cypher System Rulebook, page 390) | K98: =TRUE() -> TRUE | L98: =TRUE() -> TRUE | M98: =FALSE() -> FALSE | N98: =LEN(Table1[[#This Row],[effect]]) -> 298 | O98: =Table1[[#This Row],[name]] -> Application Nullifiant la Gravité
A99: 2024-10-01T16:53:31.722Z | B99: 2024-10-01T16:53:31.722Z | C99: 2024-10-01T16:53:31.722Z | D99: Rétaliation | E99: Retaliation | F99: Pendant le jour suivant, quiconque frappant l'utilisateur reà§oit une petite décharge d'électricité infligeant 1 point de dégâts (2 points si le cypher est de niveau 4 ou supérieur, 3 points si le cypher est de niveau 6 ou supérieur). Aucune action ou lancer n'est requis de la part de l'utilisateur. | I99: 1d6 | J99: (Cypher System Rulebook, page 396) | K99: =TRUE() -> TRUE | L99: =TRUE() -> TRUE | M99: =FALSE() -> FALSE | N99: =LEN(Table1[[#This Row],[effect]]) -> 300 | O99: =Table1[[#This Row],[name]] -> Rétaliation
A100: 2024-10-01T16:53:31.500Z | B100: 2024-10-01T16:53:31.500Z | C100: 2024-10-01T16:53:31.500Z | D100: Capteur de Mouvement | E100: Motion Sensor | F100: Pendant une heure par niveau de cypher, l'utilisateur sait quand un mouvement se produit dans la portée courte, et lorsque de grandes créatures ou objets se déplacent dans la portée longue (le cypher distingue les deux). Il indique également le nombre et la taille des créatures ou objets en mouvement. | I100: 1d6 + 2 | J100: (Cypher System Rulebook, page 393) | K100: =FALSE() -> FALSE | L100: =FALSE() -> FALSE | M100: =TRUE() -> TRUE | N100: =LEN(Table1[[#This Row],[effect]]) -> 302 | O100: =Table1[[#This Row],[name]] -> Capteur de Mouvement
...
